[{"schema":{"elements":[{"name":{"some":"id"},"algebraic_type":{"Builtin":{"I32":[]}}},{"name":{"some":"name"},"algebraic_type":{"Builtin":{"String":[]}}},{"name":{"some":"interior_instance_id"},"algebraic_type":{"Builtin":{"I32":[]}}},{"name":{"some":"spawn_x"},"algebraic_type":{"Builtin":{"I32":[]}}},{"name":{"some":"spawn_z"},"algebraic_type":{"Builtin":{"I32":[]}}},{"name":{"some":"direction"},"algebraic_type":{"Builtin":{"I32":[]}}},{"name":{"some":"spawn_type"},"algebraic_type":{"Sum":{"variants":[{"name":{"some":"Undefined"},"algebraic_type":{"Product":{"elements":[]}}},{"name":{"some":"Traveler"},"algebraic_type":{"Product":{"elements":[]}}},{"name":{"some":"Chest"},"algebraic_type":{"Product":{"elements":[]}}},{"name":{"some":"Building"},"algebraic_type":{"Product":{"elements":[]}}},{"name":{"some":"Resource"},"algebraic_type":{"Product":{"elements":[]}}},{"name":{"some":"Enemy"},"algebraic_type":{"Product":{"elements":[]}}}]}}},{"name":{"some":"building_id"},"algebraic_type":{"Builtin":{"I32":[]}}},{"name":{"some":"loot_chests"},"algebraic_type":{"Builtin":{"Array":{"Builtin":{"I32":[]}}}}},{"name":{"some":"resource_clump_id"},"algebraic_type":{"Builtin":{"I32":[]}}},{"name":{"some":"enemy_type"},"algebraic_type":{"Sum":{"variants":[{"name":{"some":"None"},"algebraic_type":{"Product":{"elements":[]}}},{"name":{"some":"PracticeDummy"},"algebraic_type":{"Product":{"elements":[]}}},{"name":{"some":"GrassBird"},"algebraic_type":{"Product":{"elements":[]}}},{"name":{"some":"Goat"},"algebraic_type":{"Product":{"elements":[]}}},{"name":{"some":"DeerFemale"},"algebraic_type":{"Product":{"elements":[]}}},{"name":{"some":"DeerMale"},"algebraic_type":{"Product":{"elements":[]}}},{"name":{"some":"BoarFemale"},"algebraic_type":{"Product":{"elements":[]}}},{"name":{"some":"BoarMale"},"algebraic_type":{"Product":{"elements":[]}}},{"name":{"some":"BoarElder"},"algebraic_type":{"Product":{"elements":[]}}},{"name":{"some":"Elk"},"algebraic_type":{"Product":{"elements":[]}}},{"name":{"some":"SwampBird"},"algebraic_type":{"Product":{"elements":[]}}},{"name":{"some":"DesertBird"},"algebraic_type":{"Product":{"elements":[]}}},{"name":{"some":"MountainGoat"},"algebraic_type":{"Product":{"elements":[]}}}]}}},{"name":{"some":"traveler_type"},"algebraic_type":{"Sum":{"variants":[{"name":{"some":"None"},"algebraic_type":{"Product":{"elements":[]}}},{"name":{"some":"Rumbagh"},"algebraic_type":{"Product":{"elements":[]}}},{"name":{"some":"Svim"},"algebraic_type":{"Product":{"elements":[]}}},{"name":{"some":"Heimlich"},"algebraic_type":{"Product":{"elements":[]}}},{"name":{"some":"Twins"},"algebraic_type":{"Product":{"elements":[]}}},{"name":{"some":"Brico"},"algebraic_type":{"Product":{"elements":[]}}}]}}},{"name":{"some":"traveler_ruin_entity_id"},"algebraic_type":{"Builtin":{"I32":[]}}},{"name":{"some":"respawn"},"algebraic_type":{"Builtin":{"Bool":[]}}},{"name":{"some":"collapse_trigger"},"algebraic_type":{"Builtin":{"Bool":[]}}}]},"rows":[[142,"Interior Spawn DesertRuinLeftRoom_142",34,-7,23,0,{"1":[]},0,[],0,{"0":[]},{"3":[]},8,true,false],[24,"Interior Spawn LeverPuzzleDungeonMainRoom_24",14,1,-1,2,{"4":[]},0,[],201,{"0":[]},{"0":[]},0,true,true],[146,"Interior Spawn DesertRuinLeftRoom_146",34,-4,21,0,{"3":[]},70000,[],0,{"0":[]},{"0":[]},0,false,false],[1209,"GreatHallWestHallwayChest3",1200,-22,5,0,{"2":[]},0,[7,8],0,{"0":[]},{"0":[]},0,true,false],[155,"Interior Spawn DesertRuinRightRoom_155",35,23,17,0,{"3":[]},70000,[],0,{"0":[]},{"0":[]},0,false,false],[189,"Interior Spawn DesertRuinRightRoom_189",35,12,3,0,{"4":[]},0,[],217,{"0":[]},{"0":[]},0,true,false],[127,"Interior Spawn LargeSturdyTownhouseLobby_127",25,-1,7,0,{"3":[]},10001,[],0,{"0":[]},{"0":[]},0,false,false],[1208,"GreatHallWestHallwayChest2",1200,-13,-8,0,{"2":[]},0,[7,8],0,{"0":[]},{"0":[]},0,true,false],[1301,"GreatHallEastHallwaySafeTorch1",1300,21,10,0,{"4":[]},0,[],167,{"0":[]},{"0":[]},0,true,false],[196,"Interior Spawn DesertRuinRightRoom_196",35,10,15,4,{"4":[]},0,[],143,{"0":[]},{"0":[]},0,true,false],[234,"Interior Spawn DesertRuinRightRoom_234",35,18,13,0,{"4":[]},0,[],216,{"0":[]},{"0":[]},0,true,false],[26019,"T2LargeRuinVine3",26000,5,-6,0,{"4":[]},0,[],175,{"0":[]},{"0":[]},0,true,false],[221,"Interior Spawn DesertRuinFinalRoom_221",36,-2,9,0,{"3":[]},70000,[],0,{"0":[]},{"0":[]},0,false,false],[111,"Interior Spawn T5SmallHouse_111",41,-2,-3,0,{"3":[]},10001,[],0,{"0":[]},{"0":[]},0,false,false],[187,"Interior Spawn DesertRuinRightRoom_187",35,16,-8,2,{"2":[]},0,[21],0,{"0":[]},{"0":[]},0,true,false],[1610,"MazeRuinRoom1BackToStartLadder2",1600,6,10,0,{"3":[]},10001,[],0,{"0":[]},{"0":[]},0,false,false],[38,"Interior Spawn LeftConnectorRoom_38",15,-8,7,2,{"4":[]},0,[],146,{"0":[]},{"0":[]},0,true,false],[131,"Interior Spawn LargeSturdyTownhouseBottomLeftRoom_131",26,2,-4,0,{"3":[]},10001,[],0,{"0":[]},{"0":[]},0,false,false],[233,"Interior Spawn DesertRuinRightRoom_233",35,21,20,10,{"2":[]},0,[21],0,{"0":[]},{"0":[]},0,true,false],[226,"Interior Spawn DesertRuinFinalRoom_226",36,1,6,0,{"2":[]},0,[21],0,{"0":[]},{"0":[]},0,true,false],[271,"Interior Spawn T6SmallHouse_271",50,-2,-3,0,{"3":[]},10001,[],0,{"0":[]},{"0":[]},0,false,false],[400,"AncientWorkbenchLadder",400,0,0,0,{"3":[]},10001,[],0,{"0":[]},{"0":[]},0,false,false],[511,"CollapsingRuinRubble11",500,8,16,0,{"4":[]},0,[],158,{"0":[]},{"0":[]},0,true,true],[240,"Interior Spawn DesertRuinMainRoom_240",33,9,2,0,{"3":[]},10001,[],0,{"0":[]},{"0":[]},0,false,false],[78,"Interior Spawn LeftPowerCoreRoom_78",17,-1,12,2,{"4":[]},0,[],146,{"0":[]},{"0":[]},0,true,false],[774,"PuzzleRuinAncientChest14",700,15,8,0,{"2":[]},0,[7,8],0,{"0":[]},{"0":[]},0,true,false],[103,"Interior Spawn SmallCaveCopper_103",100,4,1,0,{"4":[]},0,[],74,{"0":[]},{"0":[]},0,true,false],[3,"SpawnedMediumInteriorExitLadder",3,0,0,0,{"3":[]},10001,[],0,{"0":[]},{"0":[]},0,false,false],[110,"Interior Spawn SmallCaveCopper_110",100,8,5,10,{"4":[]},0,[],61,{"0":[]},{"0":[]},0,true,false],[1048,"GreatHallWestExit",1000,-4,32,0,{"3":[]},10001,[],0,{"0":[]},{"0":[]},0,false,false],[207,"TinCaveBolete",200,5,3,0,{"4":[]},0,[],79,{"0":[]},{"0":[]},0,true,false],[1051,"GreatHallWestExitExterior",1000,-13,22,0,{"3":[]},10001,[],0,{"0":[]},{"0":[]},0,false,false],[716,"PuzzleRuinSafeRubble7",700,3,14,0,{"4":[]},0,[],158,{"0":[]},{"0":[]},0,true,false],[1419,"GreatHallWestTorchRoomChest6",1400,12,1,0,{"2":[]},0,[7,8,9],0,{"0":[]},{"0":[]},0,true,false],[1552,"GreatHallEntranceCrumbledTorch",1050,-4,9,0,{"4":[]},0,[],169,{"0":[]},{"0":[]},0,true,false],[1409,"GreatHallWestTorchRoomPillar",1400,6,3,0,{"3":[]},70000,[],0,{"0":[]},{"0":[]},0,false,false],[1564,"GreatHallEntrancePillar2",1050,-5,15,0,{"3":[]},70000,[],0,{"0":[]},{"0":[]},0,false,false],[1700,"MazeRuinRoom2Entrance",1700,0,0,0,{"3":[]},10001,[],0,{"0":[]},{"0":[]},0,false,false],[215,"TinCaveTinVein2",200,6,7,0,{"4":[]},0,[],61,{"0":[]},{"0":[]},0,true,false],[1807,"MazeRuinRoom3BackToStartLadder",1800,0,16,0,{"3":[]},10001,[],0,{"0":[]},{"0":[]},0,false,false],[254,"IronCaveInteriorIronOre3",250,1,3,0,{"4":[]},0,[],62,{"0":[]},{"0":[]},0,true,true],[5106,"PrefabRuin2Chest3",5100,0,2,4,{"2":[]},0,[7,8,9,16],0,{"0":[]},{"0":[]},0,true,false],[25002,"T2PrefabRuinVines2",25000,0,-6,0,{"4":[]},0,[],175,{"0":[]},{"0":[]},0,true,false],[5109,"HeimlichT1PrefabRuin2",5100,2,2,6,{"1":[]},0,[],0,{"0":[]},{"3":[]},8,false,false],[261,"IronCaveInteriorSwampBolete2",250,4,7,0,{"4":[]},0,[],81,{"0":[]},{"0":[]},0,true,true],[314,"LargeCaveLimestoneBoulder3",300,2,25,0,{"4":[]},0,[],40,{"0":[]},{"0":[]},0,true,true],[309,"LargeCaveButtonMushrooms",300,-3,30,0,{"4":[]},0,[],74,{"0":[]},{"0":[]},0,true,false],[2101,"MazeRuinLootRoomExit",2100,6,12,0,{"3":[]},10001,[],0,{"0":[]},{"0":[]},0,false,false],[404,"AncientWorkbenchRoomChest3",400,6,11,0,{"2":[]},0,[16],0,{"0":[]},{"0":[]},0,true,false],[709,"PuzzleRuinInteriorPillar9",700,10,22,0,{"3":[]},70000,[],0,{"0":[]},{"0":[]},0,true,false],[505,"CollapsingRuinRubble5",500,12,11,0,{"4":[]},0,[],158,{"0":[]},{"0":[]},0,true,false],[513,"CollapsingRuinRubble13",500,0,15,0,{"4":[]},0,[],158,{"0":[]},{"0":[]},0,true,true],[521,"CollapsingRuinPillar2",500,13,9,0,{"3":[]},70000,[],0,{"0":[]},{"0":[]},0,true,false],[525,"CollapsingRuinPillar6",500,3,15,0,{"3":[]},70001,[],0,{"0":[]},{"0":[]},0,true,false],[603,"LargeRuinInteriorAncientChest2",600,5,45,0,{"2":[]},0,[7,8],0,{"0":[]},{"0":[]},0,true,false],[1503,"GreatHallSafeRoomHintChest",1500,6,14,0,{"2":[]},0,[13],0,{"0":[]},{"0":[]},0,true,false],[26015,"T2LargeRuinRoot2",26000,3,12,0,{"4":[]},0,[],176,{"0":[]},{"0":[]},0,true,false],[610,"LargeRuinInteriorAncientChest9",600,15,15,0,{"2":[]},0,[7,8],0,{"0":[]},{"0":[]},0,true,false],[68,"Interior Spawn LeverPuzzleDungeonMainRoom_68",14,-11,6,0,{"3":[]},10001,[],0,{"0":[]},{"0":[]},0,false,false],[1800,"MazeRuinRoom3Entrance",1800,0,0,0,{"3":[]},10001,[],0,{"0":[]},{"0":[]},0,false,false],[624,"LargeRuinInteriorRubble1",600,6,23,3,{"4":[]},0,[],158,{"0":[]},{"0":[]},0,true,false],[628,"LargeRuinInteriorVines2",600,7,41,3,{"4":[]},0,[],156,{"0":[]},{"0":[]},0,true,false],[712,"PuzzleRuinSafeRubble3",700,-13,5,0,{"4":[]},0,[],158,{"0":[]},{"0":[]},0,true,false],[1802,"MazeRuinRoom3Brazier",1800,0,10,8,{"4":[]},0,[],179,{"0":[]},{"0":[]},0,true,false],[720,"PuzzleRuinRubble1",700,-10,5,0,{"4":[]},0,[],158,{"0":[]},{"0":[]},0,true,true],[724,"PuzzleRuinRubble5",700,2,5,0,{"4":[]},0,[],158,{"0":[]},{"0":[]},0,true,true],[1600,"MazeRuinRoom1Entrance",1600,0,0,0,{"3":[]},10001,[],0,{"0":[]},{"0":[]},0,false,false],[1106,"GreatHallFinalRoomTorch4",1100,4,12,0,{"3":[]},70000,[],0,{"0":[]},{"0":[]},0,false,false],[728,"PuzzleRuinRubble9",700,14,5,0,{"4":[]},0,[],158,{"0":[]},{"0":[]},0,true,true],[135,"Interior Spawn LargeSturdyTownhouseMidRightRoom_135",30,2,-4,0,{"3":[]},10001,[],0,{"0":[]},{"0":[]},0,false,false],[242,"Interior Spawn DesertRuinRightRoom_242",35,-1,0,0,{"3":[]},10001,[],0,{"0":[]},{"0":[]},0,false,false],[106,"Interior Spawn SmallCaveCopper_106",100,5,10,0,{"4":[]},0,[],74,{"0":[]},{"0":[]},0,true,false],[705,"PuzzleRuinInteriorPillar5",700,-6,16,0,{"3":[]},70000,[],0,{"0":[]},{"0":[]},0,true,false],[5009,"Interior Spawn SingleRoomPrefabRuin1_5009",5000,2,2,6,{"1":[]},0,[],0,{"0":[]},{"3":[]},8,false,false],[5100,"PrefabRuin2Entrance",5100,0,-8,0,{"3":[]},10001,[],0,{"0":[]},{"0":[]},0,false,false],[225,"Interior Spawn DesertRuinFinalRoom_225",36,-1,6,10,{"2":[]},0,[21],0,{"0":[]},{"0":[]},0,true,false],[1020,"GreatHallTree3",1000,14,26,0,{"4":[]},0,[],176,{"0":[]},{"0":[]},0,true,false],[732,"PuzzleRuinRubble13",700,2,11,0,{"4":[]},0,[],158,{"0":[]},{"0":[]},0,true,true],[249,"Interior Spawn T4SmallHouse_249",47,-1,-2,0,{"3":[]},10001,[],0,{"0":[]},{"0":[]},0,false,false],[506,"CollapsingRuinRubble6",500,12,10,0,{"4":[]},0,[],158,{"0":[]},{"0":[]},0,true,false],[129,"Interior Spawn LargeSturdyTownhouseLobby_129",25,4,0,0,{"3":[]},10001,[],0,{"0":[]},{"0":[]},0,false,false],[22,"Interior Spawn LeverDoorRoom_22",13,0,16,0,{"4":[]},0,[],192,{"0":[]},{"0":[]},0,true,false],[1411,"GreatHallWestTorchRoomPillar3",1400,3,17,0,{"3":[]},70000,[],0,{"0":[]},{"0":[]},0,false,false],[757,"PuzzleRuinRubble37",700,3,24,0,{"4":[]},0,[],158,{"0":[]},{"0":[]},0,true,true],[1701,"MazeRuinRoom2FloorDecoration",1700,0,10,0,{"3":[]},70002,[],0,{"0":[]},{"0":[]},0,false,false],[736,"PuzzleRuinRubble17",700,-10,11,0,{"4":[]},0,[],158,{"0":[]},{"0":[]},0,true,true],[239,"Interior Spawn DesertRuinMainRoom_239",33,0,14,0,{"3":[]},10001,[],0,{"0":[]},{"0":[]},0,false,false],[745,"PuzzleRuinRubble26",700,14,17,0,{"4":[]},0,[],158,{"0":[]},{"0":[]},0,true,true],[749,"PuzzleRuinRubble30",700,-10,17,0,{"4":[]},0,[],158,{"0":[]},{"0":[]},0,true,true],[172,"Interior Spawn DesertRuinLeftRoom_172",34,-12,24,2,{"4":[]},0,[],144,{"0":[]},{"0":[]},0,true,false],[790,"Interior Spawn PuzzleRuinInterior_790",700,1,29,2,{"4":[]},0,[],143,{"0":[]},{"0":[]},0,true,false],[198,"Interior Spawn DesertRuinFinalRoom_198",36,0,6,0,{"3":[]},70002,[],0,{"0":[]},{"0":[]},0,false,false],[82,"Interior Spawn LeftPowerCoreRoom_82",17,0,0,0,{"3":[]},10001,[],0,{"0":[]},{"0":[]},0,false,false],[201,"TinCaveLimestoneBoulder",200,1,2,0,{"4":[]},0,[],46,{"0":[]},{"0":[]},0,true,true],[706,"PuzzleRuinInteriorPillar6",700,0,16,0,{"3":[]},70000,[],0,{"0":[]},{"0":[]},0,true,false],[1034,"GreatHallBrokenTorch",1000,17,18,0,{"4":[]},0,[],168,{"0":[]},{"0":[]},0,true,false],[2003,"MazeRuinRoom5Pillar1",2000,-2,8,2,{"3":[]},70000,[],0,{"0":[]},{"0":[]},0,false,false],[2012,"MazeRuinRoomSafeRubble3",2000,1,14,0,{"4":[]},0,[],158,{"0":[]},{"0":[]},0,true,false],[36,"Interior Spawn LeftConnectorRoom_36",15,-6,15,2,{"4":[]},0,[],198,{"0":[]},{"0":[]},0,true,false],[11,"SpawnedMultiRoomRightRoomExit",8,0,0,0,{"3":[]},10001,[],0,{"0":[]},{"0":[]},0,false,false],[73,"Interior Spawn LightPuzzleDungeonRoom_73",16,0,-4,0,{"3":[]},10001,[],0,{"0":[]},{"0":[]},0,false,false],[782,"PuzzleRuinAncientChest22",700,3,20,0,{"2":[]},0,[7,8],0,{"0":[]},{"0":[]},0,true,false],[1035,"GreatHallBrokenTorch2",1000,-1,14,0,{"4":[]},0,[],169,{"0":[]},{"0":[]},0,true,false],[30,"Interior Spawn LeverPuzzleDungeonMainRoom_30",14,-6,2,0,{"3":[]},70000,[],0,{"0":[]},{"0":[]},0,false,false],[1006,"GreatHallRubble2",1000,3,5,0,{"4":[]},0,[],177,{"0":[]},{"0":[]},0,true,false],[1015,"GreatHallPillar8",1000,14,17,0,{"3":[]},70000,[],0,{"0":[]},{"0":[]},0,false,false],[1022,"GreatHallAncientChest2",1000,-1,31,0,{"2":[]},0,[7,8],0,{"0":[]},{"0":[]},0,true,false],[213,"TinCaveChanterelles2",200,3,10,0,{"4":[]},0,[],79,{"0":[]},{"0":[]},0,true,false],[1028,"GreatHallAncientChest8",1000,18,1,0,{"2":[]},0,[7,8],0,{"0":[]},{"0":[]},0,true,false],[1042,"GreatHallVine2",1000,18,35,0,{"4":[]},0,[],175,{"0":[]},{"0":[]},0,true,false],[300,"LargeCaveInteriorLadder",300,0,0,0,{"3":[]},10001,[],0,{"0":[]},{"0":[]},0,false,false],[304,"LargeCaveBolete",300,-1,12,0,{"4":[]},0,[],79,{"0":[]},{"0":[]},0,true,false],[1050,"GreatHallEastExitExterior",1000,29,11,0,{"3":[]},10001,[],0,{"0":[]},{"0":[]},0,false,false],[1102,"GreatHallFinalRoomTorch2",1100,4,3,0,{"3":[]},70000,[],0,{"0":[]},{"0":[]},0,false,false],[18,"Interior Spawn LeverDoorRoom_18",13,5,0,4,{"4":[]},0,[],190,{"0":[]},{"0":[]},0,true,false],[1710,"Interior Spawn MazeRuinRoom2_1710",1700,2,13,6,{"4":[]},0,[],141,{"0":[]},{"0":[]},0,true,false],[1010,"GreatHallPillar3",1000,2,14,0,{"3":[]},70000,[],0,{"0":[]},{"0":[]},0,false,false],[1607,"MazeRuinRoom1Chest",1600,-1,2,0,{"4":[]},0,[],183,{"0":[]},{"0":[]},0,true,false],[2018,"MazeRuinRoomUnsafeRubble6",2000,6,9,0,{"4":[]},0,[],158,{"0":[]},{"0":[]},0,true,true],[1306,"GreatHallEastHallwayChest2",1300,14,10,0,{"2":[]},0,[8,9],0,{"0":[]},{"0":[]},0,true,false],[224,"Interior Spawn DesertRuinFinalRoom_224",36,2,8,4,{"4":[]},0,[],144,{"0":[]},{"0":[]},0,true,false],[1706,"MazeRuinRoom2Pillar4",1700,2,8,2,{"3":[]},70000,[],0,{"0":[]},{"0":[]},0,false,false],[1100,"GreatHallFinalRoomLadder",1100,0,0,0,{"3":[]},10001,[],0,{"0":[]},{"0":[]},0,false,false],[1108,"GreatHallFinalRoomChest2",1100,1,8,0,{"2":[]},0,[17,18],0,{"0":[]},{"0":[]},0,true,true],[25107,"Interior Spawn T2SingleRoomPrefabRuin2_25107",25100,0,4,2,{"4":[]},0,[],142,{"0":[]},{"0":[]},0,true,false],[26014,"T2LargeRuinRoot1",26000,1,11,0,{"4":[]},0,[],176,{"0":[]},{"0":[]},0,true,false],[2104,"MazeRuinLootRoomPillar3",2100,6,3,2,{"3":[]},70000,[],0,{"0":[]},{"0":[]},0,false,false],[26006,"T2LargeRuinCollapsedPillar",26000,13,2,0,{"4":[]},0,[],172,{"0":[]},{"0":[]},0,true,false],[1105,"GreatHallFinalRoomTorch3",1100,7,10,0,{"3":[]},70000,[],0,{"0":[]},{"0":[]},0,false,false],[176,"Interior Spawn DesertRuinMainRoom_176",33,-6,2,0,{"4":[]},0,[],217,{"0":[]},{"0":[]},0,true,false],[1611,"Interior Spawn MazeRuinRoom1_1611",1600,1,6,6,{"4":[]},0,[],141,{"0":[]},{"0":[]},0,true,false],[25108,"HeimlichT2PrefabRuin",25100,2,2,6,{"1":[]},0,[],0,{"0":[]},{"3":[]},8,false,false],[632,"LargeRuinInteriorRubble6",600,20,34,3,{"4":[]},0,[],158,{"0":[]},{"0":[]},0,true,true],[1407,"GreatHallWestTorchRoomExteriorExit2",1400,-7,14,0,{"3":[]},10001,[],0,{"0":[]},{"0":[]},0,false,false],[5007,"PrefabRuinNote",5000,-2,1,0,{"4":[]},0,[],185,{"0":[]},{"0":[]},0,true,false],[25004,"T2PrefabRuinChest1",25000,2,5,0,{"2":[]},0,[17],0,{"0":[]},{"0":[]},0,true,false],[770,"PuzzleRuinAncientChest10",700,-9,8,0,{"2":[]},0,[7,8],0,{"0":[]},{"0":[]},0,true,false],[26004,"T2LargeRuinPillar4",26000,3,-1,0,{"3":[]},70000,[],0,{"0":[]},{"0":[]},0,false,false],[1550,"GreatHallEntrance",1050,0,0,0,{"3":[]},10001,[],0,{"0":[]},{"0":[]},0,false,false],[27003,"T2LargeRuinTrapDoorChest2",27000,2,9,0,{"2":[]},0,[17,18],0,{"0":[]},{"0":[]},0,true,false],[1561,"GreatHallEntranceNoteChest",1050,0,10,0,{"4":[]},0,[],181,{"0":[]},{"0":[]},0,true,false],[1201,"GreatHallWestHallwayRubble",1200,-14,-2,0,{"4":[]},0,[],158,{"0":[]},{"0":[]},0,true,false],[1601,"MazeRuinRoom1FloorDecoration",1600,0,10,0,{"3":[]},70002,[],0,{"0":[]},{"0":[]},0,false,false],[29,"Interior Spawn LeverPuzzleDungeonMainRoom_29",14,3,10,0,{"3":[]},70000,[],0,{"0":[]},{"0":[]},0,false,false],[28002,"T2LargeRuinFinalRoomChest2",28000,2,9,0,{"2":[]},0,[17,18],0,{"0":[]},{"0":[]},0,true,true],[5104,"PrefabRuin2Chest1",5100,2,5,0,{"2":[]},0,[7,8,9],0,{"0":[]},{"0":[]},0,true,false],[26000,"T2LargeRuinEntrance",26000,0,0,0,{"3":[]},10001,[],0,{"0":[]},{"0":[]},0,false,false],[777,"PuzzleRuinAncientChest17",700,0,14,0,{"2":[]},0,[7,8],0,{"0":[]},{"0":[]},0,true,false],[1554,"GreatHallEntranceSafeTorch",1050,0,14,0,{"4":[]},0,[],167,{"0":[]},{"0":[]},0,true,false],[25005,"T2PrefabRuinChest2",25000,-1,5,4,{"2":[]},0,[17],0,{"0":[]},{"0":[]},0,true,false],[149,"Interior Spawn DesertRuinRightRoom_149",35,16,-12,0,{"3":[]},70000,[],0,{"0":[]},{"0":[]},0,false,false],[26020,"T2LargeRuinChest2",26000,5,-7,0,{"2":[]},0,[17],0,{"0":[]},{"0":[]},0,true,false],[5006,"PrefabRuinChest3",5000,0,2,4,{"2":[]},0,[7,8,9,16],0,{"0":[]},{"0":[]},0,true,false],[26008,"T2LargeRuinIntricateDoor",26000,14,10,10,{"4":[]},0,[],187,{"0":[]},{"0":[]},0,true,false],[26013,"T2LargeRuinChest",26000,2,12,0,{"2":[]},0,[17],0,{"0":[]},{"0":[]},0,true,false],[27005,"T2LargeRuinTrapFloorDecoration",27000,4,7,0,{"3":[]},70002,[],0,{"0":[]},{"0":[]},0,false,false],[83,"Interior Spawn LightPuzzleDungeonRoom_83",16,0,24,0,{"3":[]},10001,[],0,{"0":[]},{"0":[]},0,false,false],[758,"PuzzleRuinRubble38",700,-2,24,0,{"4":[]},0,[],158,{"0":[]},{"0":[]},0,true,true],[28005,"T2LargeRuinFinalRoomPillar1",28000,0,7,0,{"3":[]},70000,[],0,{"0":[]},{"0":[]},0,false,false],[251,"IronCaveInteriorVanadiumOre",250,1,6,0,{"4":[]},0,[],63,{"0":[]},{"0":[]},0,true,true],[1705,"MazeRuinRoom2Pillar3",1700,2,12,2,{"3":[]},70001,[],0,{"0":[]},{"0":[]},0,false,false],[26016,"T2LargeRuinRoot3",26000,2,11,0,{"4":[]},0,[],176,{"0":[]},{"0":[]},0,true,false],[301,"LargeCaveGemStalagmite",300,-3,32,0,{"4":[]},0,[],154,{"0":[]},{"0":[]},0,true,true],[1702,"MazeRuinRoom2Brazier",1700,0,10,2,{"4":[]},0,[],179,{"0":[]},{"0":[]},0,true,false],[28,"Interior Spawn LeverPuzzleDungeonMainRoom_28",14,-3,10,0,{"3":[]},70000,[],0,{"0":[]},{"0":[]},0,false,false],[602,"LargeRuinInteriorAncientChest1",600,4,46,0,{"2":[]},0,[7,8,9],0,{"0":[]},{"0":[]},0,true,false],[4,"SpawnedLargeInteriorExitLadder",4,0,0,0,{"3":[]},10001,[],0,{"0":[]},{"0":[]},0,false,false],[1001,"GreatHallCollapsingDoor1",1000,-3,16,0,{"4":[]},0,[],166,{"0":[]},{"0":[]},0,true,true],[1107,"GreatHallFinalRoomChest1",1100,4,8,0,{"2":[]},0,[19],0,{"0":[]},{"0":[]},0,true,true],[21,"Interior Spawn LeverDoorRoom_21",13,0,1,0,{"4":[]},0,[],191,{"0":[]},{"0":[]},0,true,false],[28001,"T2LargeRuinFinalRoomEndofRunChest",28000,4,8,0,{"2":[]},0,[19],0,{"0":[]},{"0":[]},0,true,true],[1007,"GreatHallRubble3",1000,3,4,0,{"4":[]},0,[],177,{"0":[]},{"0":[]},0,true,false],[113,"Interior Spawn SmallEnterableHutTier2_113",44,-1,-2,0,{"3":[]},10001,[],0,{"0":[]},{"0":[]},0,false,false],[268,"Interior Spawn HeimlichsHouse_268",40,0,-1,0,{"3":[]},60,[],0,{"0":[]},{"0":[]},0,false,false],[759,"PuzzleRuinRubble39",700,-7,24,0,{"4":[]},0,[],158,{"0":[]},{"0":[]},0,true,true],[41,"Interior Spawn LightPuzzleDungeonRoom_41",16,-2,1,0,{"4":[]},0,[],201,{"0":[]},{"0":[]},0,true,false],[45,"Interior Spawn LightPuzzleDungeonRoom_45",16,-9,13,0,{"4":[]},0,[],201,{"0":[]},{"0":[]},0,true,false],[1016,"GreatHallPillar9",1000,8,26,0,{"3":[]},70000,[],0,{"0":[]},{"0":[]},0,false,false],[49,"Interior Spawn LightPuzzleDungeonRoom_49",16,4,1,0,{"4":[]},0,[],202,{"0":[]},{"0":[]},0,true,false],[2011,"MazeRuinRoomSafeRubble2",2000,-1,14,0,{"4":[]},0,[],158,{"0":[]},{"0":[]},0,true,false],[1704,"MazeRuinRoom2Pillar2",1700,-2,12,2,{"3":[]},70001,[],0,{"0":[]},{"0":[]},0,false,false],[148,"Interior Spawn DesertRuinRightRoom_148",35,12,-6,0,{"3":[]},70000,[],0,{"0":[]},{"0":[]},0,false,false],[1907,"MazeRuinRoom4BackToStartLadder",1900,0,16,0,{"3":[]},10001,[],0,{"0":[]},{"0":[]},0,false,false],[257,"IronCaveInteriorSandstoneDeposit2",250,0,2,0,{"4":[]},0,[],48,{"0":[]},{"0":[]},0,true,true],[53,"Interior Spawn LightPuzzleDungeonRoom_53",16,1,3,2,{"4":[]},0,[],202,{"0":[]},{"0":[]},0,true,false],[500,"SpawnedExitCollapsingRuin",500,0,0,0,{"3":[]},10001,[],0,{"0":[]},{"0":[]},0,false,false],[618,"LargeRuinInteriorPillar3",600,31,38,0,{"3":[]},70000,[],0,{"0":[]},{"0":[]},0,true,false],[58,"Interior Spawn LightPuzzleDungeonRoom_58",16,10,7,0,{"4":[]},0,[],202,{"0":[]},{"0":[]},0,true,false],[702,"PuzzleRuinInteriorPillar2",700,-13,0,0,{"3":[]},70000,[],0,{"0":[]},{"0":[]},0,true,false],[1204,"GreatHallWestHallwayVines2",1200,-18,6,0,{"4":[]},0,[],156,{"0":[]},{"0":[]},0,true,false],[97,"Interior Spawn Final Reward Room_97",19,4,12,2,{"4":[]},0,[],146,{"0":[]},{"0":[]},0,true,false],[1562,"GreatHallEntranceDecoration",1050,0,10,0,{"3":[]},70002,[],0,{"0":[]},{"0":[]},0,false,false],[62,"Interior Spawn LightPuzzleDungeonRoom_62",16,1,9,2,{"4":[]},0,[],202,{"0":[]},{"0":[]},0,true,false],[35,"Interior Spawn LeftConnectorRoom_35",15,-5,22,0,{"4":[]},0,[],196,{"0":[]},{"0":[]},0,true,false],[2106,"MazeMainRewardChest",2100,4,8,0,{"2":[]},0,[15],0,{"0":[]},{"0":[]},0,true,true],[124,"Interior Spawn LargeSturdyTownhouseLobby_124",25,-2,-3,0,{"3":[]},10001,[],0,{"0":[]},{"0":[]},0,false,false],[1909,"MazeRuinRoom4BackToStartLadder2",1900,6,10,0,{"3":[]},10001,[],0,{"0":[]},{"0":[]},0,false,false],[502,"CollapsingRuinRubble2",500,12,12,0,{"4":[]},0,[],158,{"0":[]},{"0":[]},0,true,false],[217,"TinCaveBolete6",200,-1,6,0,{"4":[]},0,[],79,{"0":[]},{"0":[]},0,true,false],[177,"Interior Spawn DesertRuinMainRoom_177",33,-6,1,0,{"4":[]},0,[],217,{"0":[]},{"0":[]},0,true,false],[182,"Interior Spawn DesertRuinMainRoom_182",33,1,9,2,{"4":[]},0,[],222,{"0":[]},{"0":[]},0,true,false],[604,"LargeRuinInteriorAncientChest3",600,5,46,0,{"2":[]},0,[7,8],0,{"0":[]},{"0":[]},0,true,false],[622,"LargeRuinInteriorRoot1",600,12,16,3,{"4":[]},0,[],157,{"0":[]},{"0":[]},0,true,false],[619,"LargeRuinInteriorPillar4",600,31,32,0,{"3":[]},70000,[],0,{"0":[]},{"0":[]},0,true,false],[145,"Interior Spawn DesertRuinLeftRoom_145",34,-4,25,0,{"3":[]},70000,[],0,{"0":[]},{"0":[]},0,false,false],[2000,"MazeRuinRoom5Entrance",2000,0,0,0,{"3":[]},10001,[],0,{"0":[]},{"0":[]},0,false,false],[26,"Interior Spawn LeverPuzzleDungeonMainRoom_26",14,3,2,0,{"3":[]},70000,[],0,{"0":[]},{"0":[]},0,false,false],[95,"Interior Spawn Final Reward Room_95",19,0,0,0,{"3":[]},10001,[],0,{"0":[]},{"0":[]},0,false,false],[192,"Interior Spawn DesertRuinRightRoom_192",35,25,12,2,{"2":[]},0,[21],0,{"0":[]},{"0":[]},0,true,false],[614,"LargeRuinInteriorAncientChest13",600,35,28,0,{"2":[]},0,[7,8],0,{"0":[]},{"0":[]},0,true,false],[766,"PuzzleRuinAncientChest6",700,0,2,0,{"2":[]},0,[7,8],0,{"0":[]},{"0":[]},0,true,false],[219,"TinCaveChanterelles3",200,1,6,0,{"4":[]},0,[],79,{"0":[]},{"0":[]},0,true,false],[173,"Interior Spawn DesertRuinLeftRoom_173",34,-3,24,6,{"4":[]},0,[],144,{"0":[]},{"0":[]},0,true,false],[185,"Interior Spawn DesertRuinRightRoom_185",35,6,-3,0,{"4":[]},0,[],216,{"0":[]},{"0":[]},0,true,false],[1047,"GreatHallAncientChest18",1000,14,12,0,{"2":[]},0,[7,8],0,{"0":[]},{"0":[]},0,true,false],[2002,"MazeRuinRoom5Brazier",2000,0,10,5,{"4":[]},0,[],174,{"0":[]},{"0":[]},0,true,false],[269,"Interior Spawn DesertRuinLeftRoom_269",34,-6,21,0,{"3":[]},60,[],0,{"0":[]},{"0":[]},0,false,false],[158,"Interior Spawn DesertRuinRightRoom_158",35,29,7,0,{"3":[]},70000,[],0,{"0":[]},{"0":[]},0,false,false],[246,"Interior Spawn T3LargeHouse_246",39,0,0,0,{"3":[]},10001,[],0,{"0":[]},{"0":[]},0,false,false],[194,"Interior Spawn DesertRuinRightRoom_194",35,26,13,2,{"2":[]},0,[21],0,{"0":[]},{"0":[]},0,true,false],[1703,"MazeRuinRoom2Pillar1",1700,-2,8,2,{"3":[]},70001,[],0,{"0":[]},{"0":[]},0,false,false],[2010,"MazeRuinRoomSafeRubble1",2000,0,14,0,{"4":[]},0,[],158,{"0":[]},{"0":[]},0,true,false],[26010,"T2LargeRuinRubble2",26000,7,13,0,{"4":[]},0,[],177,{"0":[]},{"0":[]},0,true,false],[231,"Interior Spawn DesertRuinRightRoom_231",35,28,19,6,{"4":[]},0,[],141,{"0":[]},{"0":[]},0,true,false],[27002,"T2LargeRuinTrapDoorChest",27000,6,6,0,{"2":[]},0,[17,18],0,{"0":[]},{"0":[]},0,true,false],[28000,"T2LargeRuinFinalRoomDoorEntrance",28000,0,0,0,{"3":[]},10001,[],0,{"0":[]},{"0":[]},0,false,false],[256,"IronCaveInteriorSandstoneDeposit",250,3,2,0,{"4":[]},0,[],48,{"0":[]},{"0":[]},0,true,true],[28004,"T2LargeRuinFinalRoomFloorDecor",28000,4,8,0,{"3":[]},70002,[],0,{"0":[]},{"0":[]},0,false,false],[25,"Interior Spawn LeverPuzzleDungeonMainRoom_25",14,0,6,0,{"3":[]},70002,[],0,{"0":[]},{"0":[]},0,false,false],[5,"SpawnedMultiRoomExit",5,0,0,0,{"3":[]},10001,[],0,{"0":[]},{"0":[]},0,false,false],[220,"Interior Spawn DesertRuinFinalRoom_220",36,3,3,0,{"3":[]},70000,[],0,{"0":[]},{"0":[]},0,false,false],[25106,"T2PrefabRuin2Chest3",25100,0,2,4,{"2":[]},0,[17,18],0,{"0":[]},{"0":[]},0,true,false],[28010,"Interior Spawn T2LargeRuinFinalRoom_28010",28000,4,12,2,{"4":[]},0,[],144,{"0":[]},{"0":[]},0,true,false],[229,"Interior Spawn DesertRuinFinalRoom_229",36,-4,5,10,{"2":[]},0,[21],0,{"0":[]},{"0":[]},0,true,false],[402,"AncientWorkbenchRoomChest",400,3,10,0,{"2":[]},0,[9],0,{"0":[]},{"0":[]},0,true,false],[739,"PuzzleRuinRubble20",700,0,8,0,{"4":[]},0,[],158,{"0":[]},{"0":[]},0,true,true],[188,"Interior Spawn DesertRuinRightRoom_188",35,16,-10,2,{"2":[]},0,[21],0,{"0":[]},{"0":[]},0,true,false],[115,"Interior Spawn LargeEnterableHutTier2_115",46,-1,-2,0,{"3":[]},10001,[],0,{"0":[]},{"0":[]},0,false,false],[147,"Interior Spawn DesertRuinRightRoom_147",35,12,-12,0,{"3":[]},70000,[],0,{"0":[]},{"0":[]},0,false,false],[714,"PuzzleRuinSafeRubble5",700,-9,14,0,{"4":[]},0,[],158,{"0":[]},{"0":[]},0,true,false],[186,"Interior Spawn DesertRuinRightRoom_186",35,16,-9,2,{"2":[]},0,[21],0,{"0":[]},{"0":[]},0,true,false],[210,"TinCaveBolete4",200,2,4,0,{"4":[]},0,[],79,{"0":[]},{"0":[]},0,true,false],[265,"IronCaveInteriorSwampBolete4",250,0,8,0,{"4":[]},0,[],81,{"0":[]},{"0":[]},0,true,true],[270,"Interior Spawn T4LargeHouse_270",49,-1,-1,0,{"3":[]},10001,[],0,{"0":[]},{"0":[]},0,false,false],[17,"Interior Spawn LeverDoorRoom_17",13,0,0,0,{"4":[]},0,[],189,{"0":[]},{"0":[]},0,true,false],[101,"CopperCaveCopperOutcrop",100,4,7,0,{"4":[]},0,[],155,{"0":[]},{"0":[]},0,true,true],[2,"SpawnedSmallInteriorExitLadder",2,0,0,0,{"3":[]},10001,[],0,{"0":[]},{"0":[]},0,false,false],[109,"Interior Spawn SmallCaveCopper_109",100,1,3,0,{"4":[]},0,[],58,{"0":[]},{"0":[]},0,true,false],[1605,"MazeRuinRoom1Pillar3",1600,2,12,2,{"3":[]},70001,[],0,{"0":[]},{"0":[]},0,false,false],[27000,"T2LargeRuinTrapDoorEntrance",27000,0,0,0,{"3":[]},10001,[],0,{"0":[]},{"0":[]},0,false,false],[205,"TinCaveLimestoneBoulder5",200,7,5,0,{"4":[]},0,[],46,{"0":[]},{"0":[]},0,true,false],[116,"Interior Spawn SmallSturdyTownhouseLobby_116",20,-4,0,0,{"3":[]},10001,[],0,{"0":[]},{"0":[]},0,false,false],[318,"LargeCaveButtonMushrooms5",300,4,20,0,{"4":[]},0,[],74,{"0":[]},{"0":[]},0,true,false],[1417,"GreatHallWestTorchRoomChest4",1400,-6,13,0,{"2":[]},0,[7,8,9],0,{"0":[]},{"0":[]},0,true,false],[67,"Interior Spawn LeverPuzzleDungeonMainRoom_67",14,11,6,0,{"3":[]},10001,[],0,{"0":[]},{"0":[]},0,false,false],[212,"TinCaveChanterelles",200,4,5,0,{"4":[]},0,[],79,{"0":[]},{"0":[]},0,true,false],[25101,"T2PrefabRuin2Roots",25100,-1,-6,0,{"4":[]},0,[],176,{"0":[]},{"0":[]},0,true,false],[253,"IronCaveInteriorIronOre2",250,6,3,0,{"4":[]},0,[],62,{"0":[]},{"0":[]},0,true,true],[33,"Interior Spawn LeverPuzzleDungeonMainRoom_33",14,6,2,0,{"3":[]},70000,[],0,{"0":[]},{"0":[]},0,false,false],[121,"Interior Spawn SmallSturdyTownhouseTopLeftRoom_121",22,2,-4,0,{"3":[]},10001,[],0,{"0":[]},{"0":[]},0,false,false],[260,"IronCaveInteriorSwampBolete",250,-1,5,0,{"4":[]},0,[],81,{"0":[]},{"0":[]},0,true,true],[27011,"Interior Spawn T2LargeRuinTrapDoor_27011",27000,4,12,2,{"4":[]},0,[],143,{"0":[]},{"0":[]},0,true,false],[74,"Interior Spawn LeftPowerCoreRoom_74",17,0,8,0,{"4":[]},0,[],200,{"0":[]},{"0":[]},0,true,false],[303,"LargeCaveCopperVein2",300,-6,12,0,{"4":[]},0,[],58,{"0":[]},{"0":[]},0,true,false],[90,"Interior Spawn LeverDoorRoom_90",13,-1,18,2,{"4":[]},0,[],143,{"0":[]},{"0":[]},0,true,false],[312,"LargeCaveLimestoneBoulder1",300,1,5,0,{"4":[]},0,[],40,{"0":[]},{"0":[]},0,true,false],[5010,"Interior Spawn SingleRoomPrefabRuin1_5010",5000,-2,2,10,{"3":[]},60,[],0,{"0":[]},{"0":[]},0,false,false],[401,"AncientWorkbenchWorkbenchRoom",400,4,7,1,{"1":[]},0,[],0,{"0":[]},{"1":[]},8,true,false],[503,"CollapsingRuinRubble3",500,12,13,0,{"4":[]},0,[],158,{"0":[]},{"0":[]},0,true,false],[241,"Interior Spawn DesertRuinLeftRoom_241",34,3,0,0,{"3":[]},10001,[],0,{"0":[]},{"0":[]},0,false,false],[510,"CollapsingRuinRubble10",500,9,15,0,{"4":[]},0,[],158,{"0":[]},{"0":[]},0,true,true],[26023,"T2LargeRuinRubble5",26000,2,7,0,{"4":[]},0,[],177,{"0":[]},{"0":[]},0,true,false],[520,"CollapsingRuinPillar1",500,11,13,0,{"3":[]},70000,[],0,{"0":[]},{"0":[]},0,true,false],[1400,"GreatHallWestTorchRoomLadder",1400,0,0,0,{"3":[]},10001,[],0,{"0":[]},{"0":[]},0,false,false],[524,"CollapsingRuinPillar5",500,-1,15,0,{"3":[]},70001,[],0,{"0":[]},{"0":[]},0,true,false],[1808,"MazeRuinRoom3BackToStartLadder2",1800,-6,10,0,{"3":[]},10001,[],0,{"0":[]},{"0":[]},0,false,false],[66,"Interior Spawn LeverPuzzleDungeonMainRoom_66",14,0,-4,0,{"3":[]},10001,[],0,{"0":[]},{"0":[]},0,false,false],[136,"Interior Spawn LargeSturdyTownhouseBottomRightRoom_136",31,2,-4,0,{"3":[]},10001,[],0,{"0":[]},{"0":[]},0,false,false],[601,"LargeRuinInteriorAncientWorkbenchExit",600,-4,25,0,{"3":[]},10001,[],0,{"0":[]},{"0":[]},0,false,false],[784,"PuzzleRuinAncientChest24",700,-10,20,0,{"2":[]},0,[7,8],0,{"0":[]},{"0":[]},0,true,false],[26011,"T2LargeRuinRubble3",26000,8,12,0,{"4":[]},0,[],177,{"0":[]},{"0":[]},0,true,false],[1402,"GreatHallWestTorchRoomGate2",1400,0,18,0,{"4":[]},0,[],166,{"0":[]},{"0":[]},0,true,true],[302,"LargeCaveCopperVein",300,-7,10,0,{"4":[]},0,[],58,{"0":[]},{"0":[]},0,true,false],[5110,"Interior Spawn SingleRoomPrefabRuin2_5010",5100,-2,2,10,{"3":[]},60,[],0,{"0":[]},{"0":[]},0,false,false],[1558,"GreatHallEntranceVine",1050,-1,2,0,{"4":[]},0,[],175,{"0":[]},{"0":[]},0,true,false],[2017,"MazeRuinRoomUnsafeRubble5",2000,5,10,0,{"4":[]},0,[],158,{"0":[]},{"0":[]},0,true,true],[28003,"T2LargeRuinFinalRoomChest3",28000,6,6,0,{"2":[]},0,[17,18],0,{"0":[]},{"0":[]},0,true,true],[609,"LargeRuinInteriorAncientChest8",600,15,17,0,{"2":[]},0,[7,8],0,{"0":[]},{"0":[]},0,true,false],[623,"LargeRuinInteriorRoot2",600,13,15,3,{"4":[]},0,[],157,{"0":[]},{"0":[]},0,true,false],[1900,"MazeRuinRoom4Entrance",1900,0,0,0,{"3":[]},10001,[],0,{"0":[]},{"0":[]},0,false,false],[627,"LargeRuinInteriorVines1",600,6,41,3,{"4":[]},0,[],156,{"0":[]},{"0":[]},0,true,false],[26002,"T2LargeRuinPillar2",26000,12,4,0,{"3":[]},70001,[],0,{"0":[]},{"0":[]},0,false,false],[26007,"T2LargeRuinTrapDoor",26000,13,2,0,{"3":[]},10006,[],0,{"0":[]},{"0":[]},0,false,false],[636,"Interior Spawn LargeRuinInterior_636",600,14,17,6,{"4":[]},0,[],142,{"0":[]},{"0":[]},0,true,false],[718,"PuzzleRuinSafeRubble9",700,8,17,0,{"4":[]},0,[],158,{"0":[]},{"0":[]},0,true,false],[94,"Interior Spawn LeverPuzzleDungeonMainRoom_94",14,0,16,0,{"3":[]},10001,[],0,{"0":[]},{"0":[]},0,false,false],[1553,"GreatHallEntranceCrumbledTorch2",1050,3,9,0,{"4":[]},0,[],169,{"0":[]},{"0":[]},0,true,false],[171,"Interior Spawn DesertRuinLeftRoom_171",34,-25,-9,4,{"2":[]},0,[21],0,{"0":[]},{"0":[]},0,true,false],[1404,"GreatHallWestTorchRoomGate4",1400,13,9,0,{"4":[]},0,[],165,{"0":[]},{"0":[]},0,true,false],[1206,"GreatHallWestHallwayComplicatedDoor",1200,-15,19,2,{"4":[]},0,[],159,{"0":[]},{"0":[]},0,true,false],[1707,"MazeRuinRoom2BackToStartLadder",1700,0,16,0,{"3":[]},10001,[],0,{"0":[]},{"0":[]},0,false,false],[778,"PuzzleRuinAncientChest18",700,-6,14,0,{"2":[]},0,[7,8],0,{"0":[]},{"0":[]},0,true,false],[1708,"MazeRuinRoom2NextRoomLadder",1700,-6,10,0,{"3":[]},10001,[],0,{"0":[]},{"0":[]},0,false,false],[723,"PuzzleRuinRubble4",700,-1,5,0,{"4":[]},0,[],158,{"0":[]},{"0":[]},0,true,true],[727,"PuzzleRuinRubble8",700,11,5,0,{"4":[]},0,[],158,{"0":[]},{"0":[]},0,true,true],[731,"PuzzleRuinRubble12",700,5,11,0,{"4":[]},0,[],158,{"0":[]},{"0":[]},0,true,true],[26018,"T2LargeRuinVine2",26000,4,-6,0,{"4":[]},0,[],175,{"0":[]},{"0":[]},0,true,false],[26012,"T2LargeRuinRubble4",26000,10,16,0,{"4":[]},0,[],177,{"0":[]},{"0":[]},0,true,false],[735,"PuzzleRuinRubble16",700,-7,11,0,{"4":[]},0,[],158,{"0":[]},{"0":[]},0,true,true],[744,"PuzzleRuinRubble25",700,11,17,0,{"4":[]},0,[],158,{"0":[]},{"0":[]},0,true,true],[263,"IronCaveInteriorBolete",250,2,4,0,{"4":[]},0,[],79,{"0":[]},{"0":[]},0,true,true],[748,"PuzzleRuinRubble29",700,-7,17,0,{"4":[]},0,[],158,{"0":[]},{"0":[]},0,true,true],[9,"SpawnedMultiRoomLeftRoomExit",6,0,0,0,{"3":[]},10001,[],0,{"0":[]},{"0":[]},0,false,false],[787,"PuzzleRuinClue",700,0,1,0,{"4":[]},0,[],184,{"0":[]},{"0":[]},0,true,false],[170,"Interior Spawn DesertRuinLeftRoom_170",34,-28,-9,0,{"2":[]},0,[21],0,{"0":[]},{"0":[]},0,true,false],[1416,"GreatHallWestTorchRoomChest3",1400,-3,19,0,{"2":[]},0,[7,8,9],0,{"0":[]},{"0":[]},0,true,false],[738,"PuzzleRuinRubble19",700,6,8,0,{"4":[]},0,[],158,{"0":[]},{"0":[]},0,true,true],[617,"LargeRuinInteriorPillar2",600,34,38,0,{"3":[]},70000,[],0,{"0":[]},{"0":[]},0,true,false],[764,"PuzzleRuinAncientChest4",700,12,2,0,{"2":[]},0,[7,8],0,{"0":[]},{"0":[]},0,true,false],[786,"PuzzleRuinRubble40",700,3,2,0,{"4":[]},0,[],158,{"0":[]},{"0":[]},0,true,true],[13,"SpawnedT2MediumInteriorExitLadder",10,0,0,0,{"3":[]},10001,[],0,{"0":[]},{"0":[]},0,false,false],[1005,"GreatHallRubble1",1000,2,5,0,{"4":[]},0,[],177,{"0":[]},{"0":[]},0,true,false],[1026,"GreatHallAncientChest6",1000,26,12,0,{"2":[]},0,[7,8],0,{"0":[]},{"0":[]},0,true,false],[235,"Interior Spawn DesertRuinMainRoom_235",33,0,-10,0,{"3":[]},10001,[],0,{"0":[]},{"0":[]},0,false,false],[166,"Interior Spawn DesertRuinLeftRoom_166",34,-7,16,0,{"4":[]},0,[],217,{"0":[]},{"0":[]},0,true,false],[703,"PuzzleRuinInteriorPillar3",700,-16,10,0,{"3":[]},70000,[],0,{"0":[]},{"0":[]},0,true,false],[1003,"GreatHallSafeDoor1",1000,3,28,0,{"4":[]},0,[],165,{"0":[]},{"0":[]},0,true,false],[32,"Interior Spawn LeverPuzzleDungeonMainRoom_32",14,6,10,0,{"3":[]},70000,[],0,{"0":[]},{"0":[]},0,false,false],[183,"Interior Spawn DesertRuinMainRoom_183",33,4,8,0,{"2":[]},0,[21],0,{"0":[]},{"0":[]},0,true,false],[108,"Interior Spawn SmallCaveCopper_108",100,0,8,0,{"4":[]},0,[],58,{"0":[]},{"0":[]},0,true,false],[209,"TinCaveBolete3",200,5,6,0,{"4":[]},0,[],79,{"0":[]},{"0":[]},0,true,false],[765,"PuzzleRuinAncientChest5",700,6,2,0,{"2":[]},0,[7,8],0,{"0":[]},{"0":[]},0,true,false],[1013,"GreatHallPillar6",1000,12,13,0,{"3":[]},70000,[],0,{"0":[]},{"0":[]},0,false,false],[788,"Interior Spawn PuzzleRuinInterior_788",700,2,38,4,{"4":[]},0,[],141,{"0":[]},{"0":[]},0,true,false],[1019,"GreatHallTree2",1000,14,27,0,{"4":[]},0,[],176,{"0":[]},{"0":[]},0,true,false],[1025,"GreatHallAncientChest5",1000,27,13,0,{"2":[]},0,[7,8],0,{"0":[]},{"0":[]},0,true,false],[1203,"GreatHallWestHallwayVines",1200,-18,7,0,{"4":[]},0,[],156,{"0":[]},{"0":[]},0,true,false],[1556,"GreatHallEntranceRubbleBuilding",1050,-7,9,0,{"3":[]},70003,[],0,{"0":[]},{"0":[]},0,false,false],[1906,"MazeRuinRoom4Pillar4",1900,2,8,2,{"3":[]},70000,[],0,{"0":[]},{"0":[]},0,false,false],[5008,"Interior Spawn SingleRoomPrefabRuin1_5008",5000,0,4,6,{"4":[]},0,[],141,{"0":[]},{"0":[]},0,true,false],[1039,"GreatHallAncientChest14",1000,16,33,0,{"2":[]},0,[8,9],0,{"0":[]},{"0":[]},0,true,false],[134,"Interior Spawn LargeSturdyTownhouseTopRightRoom_134",29,2,-4,0,{"3":[]},10001,[],0,{"0":[]},{"0":[]},0,false,false],[1049,"GreatHallEastExit",1000,20,1,0,{"3":[]},10001,[],0,{"0":[]},{"0":[]},0,false,false],[1905,"MazeRuinRoom4Pillar3",1900,2,12,2,{"3":[]},70000,[],0,{"0":[]},{"0":[]},0,false,false],[2110,"MazeRuinLootChest2",2100,6,6,0,{"2":[]},0,[16],0,{"0":[]},{"0":[]},0,true,true],[26025,"T2LargeRuinRubble7",26000,3,6,0,{"4":[]},0,[],177,{"0":[]},{"0":[]},0,true,false],[27001,"T2LargeRuinTrapDoorAncientWorkbench",27000,4,8,0,{"1":[]},0,[],0,{"0":[]},{"4":[]},8,true,false],[1101,"GreatHallFinalRoomTorch",1100,1,5,0,{"3":[]},70000,[],0,{"0":[]},{"0":[]},0,false,false],[710,"PuzzleRuinSafeRubble1",700,-3,2,0,{"4":[]},0,[],158,{"0":[]},{"0":[]},0,true,false],[1405,"GreatHallWestTorchRoomSafeRoomExit",1400,17,6,0,{"3":[]},10001,[],0,{"0":[]},{"0":[]},0,false,false],[1307,"GreatHallEastHallwayFloorDecoration",1300,14,11,0,{"3":[]},70002,[],0,{"0":[]},{"0":[]},0,false,false],[119,"Interior Spawn SmallSturdyTownhouseLobby_119",20,2,-4,0,{"3":[]},10001,[],0,{"0":[]},{"0":[]},0,false,false],[159,"Interior Spawn DesertRuinMainRoom_159",33,-2,8,0,{"3":[]},10005,[],0,{"0":[]},{"0":[]},0,false,false],[1563,"GreatHallEntrancePillar1",1050,-5,3,0,{"3":[]},70000,[],0,{"0":[]},{"0":[]},0,false,false],[5101,"PrefabRuin2Roots",5100,-1,-6,0,{"4":[]},0,[],157,{"0":[]},{"0":[]},0,true,false],[25000,"T2PrefabRuinEntrance",25000,0,-8,0,{"3":[]},10001,[],0,{"0":[]},{"0":[]},0,false,false],[2016,"MazeRuinRoomUnsafeRubble4",2000,6,11,0,{"4":[]},0,[],158,{"0":[]},{"0":[]},0,true,true],[2103,"MazeRuinLootRoomPillar2",2100,0,7,2,{"3":[]},70000,[],0,{"0":[]},{"0":[]},0,false,false],[151,"Interior Spawn DesertRuinRightRoom_151",35,9,8,0,{"3":[]},70000,[],0,{"0":[]},{"0":[]},0,false,false],[311,"LargeCaveButtonMushrooms3",300,-6,30,0,{"4":[]},0,[],74,{"0":[]},{"0":[]},0,true,false],[1302,"GreatHallEastHallwayTorch2",1300,9,18,0,{"4":[]},0,[],168,{"0":[]},{"0":[]},0,true,false],[5005,"PrefabRuinChest2",5000,-1,5,4,{"2":[]},0,[7,8,9],0,{"0":[]},{"0":[]},0,true,false],[26009,"T2LargeRuinRubble1",26000,7,12,0,{"4":[]},0,[],177,{"0":[]},{"0":[]},0,true,false],[1414,"GreatHallWestTorchRoomChest1",1400,3,12,0,{"2":[]},0,[8,9],0,{"0":[]},{"0":[]},0,true,false],[514,"CollapsingRuinRubble14",500,0,16,0,{"4":[]},0,[],158,{"0":[]},{"0":[]},0,true,true],[2001,"MazeRuinRoom5FloorDecoration",2000,0,10,0,{"3":[]},70002,[],0,{"0":[]},{"0":[]},0,false,false],[25102,"T2PrefabRuin2Roots2",25100,0,-6,0,{"4":[]},0,[],176,{"0":[]},{"0":[]},0,true,false],[633,"Interior Spawn LargeRuinInterior_633",600,3,48,4,{"4":[]},0,[],141,{"0":[]},{"0":[]},0,true,false],[92,"Interior Spawn RightPowerCoreRoom_92",18,1,5,10,{"2":[]},0,[18],0,{"0":[]},{"0":[]},0,true,false],[120,"Interior Spawn SmallSturdyTownhouseBottomLeftRoom_120",21,2,-4,0,{"3":[]},10001,[],0,{"0":[]},{"0":[]},0,false,false],[1205,"GreatHallWestHallwayVines3",1200,-18,5,0,{"4":[]},0,[],156,{"0":[]},{"0":[]},0,true,false],[154,"Interior Spawn DesertRuinRightRoom_154",35,15,16,0,{"3":[]},70000,[],0,{"0":[]},{"0":[]},0,false,false],[150,"Interior Spawn DesertRuinRightRoom_150",35,16,-6,0,{"3":[]},70000,[],0,{"0":[]},{"0":[]},0,false,false],[125,"Interior Spawn LargeSturdyTownhouseLobby_125",25,-4,1,0,{"3":[]},10001,[],0,{"0":[]},{"0":[]},0,false,false],[27010,"Interior Spawn T2LargeRuinTrapDoor_27010",27000,7,10,4,{"4":[]},0,[],143,{"0":[]},{"0":[]},0,true,false],[107,"Interior Spawn SmallCaveCopper_107",100,5,2,0,{"4":[]},0,[],58,{"0":[]},{"0":[]},0,true,false],[772,"PuzzleRuinAncientChest12",700,3,8,0,{"2":[]},0,[7,8],0,{"0":[]},{"0":[]},0,true,false],[1403,"GreatHallWestTorchRoomGate3",1400,10,3,0,{"4":[]},0,[],166,{"0":[]},{"0":[]},0,true,true],[611,"LargeRuinInteriorAncientChest10",600,33,36,0,{"2":[]},0,[7,8,9],0,{"0":[]},{"0":[]},0,true,false],[753,"PuzzleRuinRubble34",700,9,14,0,{"4":[]},0,[],158,{"0":[]},{"0":[]},0,true,true],[630,"LargeRuinInteriorRubble4",600,21,36,3,{"4":[]},0,[],158,{"0":[]},{"0":[]},0,true,true],[2107,"MazeRuinLootDecor",2100,4,8,0,{"3":[]},70002,[],0,{"0":[]},{"0":[]},0,false,false],[1603,"MazeRuinRoom1Pillar1",1600,-2,8,2,{"3":[]},70001,[],0,{"0":[]},{"0":[]},0,false,false],[26027,"T2LargeRuinChest4",26000,-1,7,0,{"2":[]},0,[17],0,{"0":[]},{"0":[]},0,true,false],[767,"PuzzleRuinAncientChest7",700,-6,2,0,{"2":[]},0,[7,8],0,{"0":[]},{"0":[]},0,true,false],[26022,"T2LargeRuinFinalRoomEntrance",26000,15,10,0,{"3":[]},10001,[],0,{"0":[]},{"0":[]},0,false,false],[1805,"MazeRuinRoom3Pillar3",1800,2,12,2,{"3":[]},70000,[],0,{"0":[]},{"0":[]},0,false,false],[15,"Interior Spawn WindmillInteriorInstance_15",12,-2,-4,0,{"3":[]},10001,[],0,{"0":[]},{"0":[]},0,false,false],[1,"SpawnedHutInteriorExitLadder",1,2,-4,0,{"3":[]},10001,[],0,{"0":[]},{"0":[]},0,false,false],[14,"SpawnedT2LargeInteriorExitLadder",11,0,0,0,{"3":[]},10001,[],0,{"0":[]},{"0":[]},0,false,false],[305,"LargeCaveBolete2",300,0,10,0,{"4":[]},0,[],79,{"0":[]},{"0":[]},0,true,false],[1027,"GreatHallAncientChest7",1000,18,2,0,{"2":[]},0,[7,8],0,{"0":[]},{"0":[]},0,true,false],[1500,"GreatHallSafeRoomEntrance",1500,0,0,0,{"3":[]},10001,[],0,{"0":[]},{"0":[]},0,false,false],[123,"Interior Spawn SmallSturdyTownhouseBottomRightRoom_123",24,2,-4,0,{"3":[]},10001,[],0,{"0":[]},{"0":[]},0,false,false],[1509,"Interior Spawn GreatHallSafeRoom_1509",1500,6,18,6,{"4":[]},0,[],143,{"0":[]},{"0":[]},0,true,false],[1810,"Interior Spawn MazeRuinRoom3_1810",1800,-1,6,2,{"4":[]},0,[],141,{"0":[]},{"0":[]},0,true,false],[2005,"MazeRuinRoom5Pillar3",2000,2,12,2,{"3":[]},70000,[],0,{"0":[]},{"0":[]},0,false,false],[26001,"T2LargeRuinPillar1",26000,9,10,0,{"3":[]},70000,[],0,{"0":[]},{"0":[]},0,false,false],[768,"PuzzleRuinAncientChest8",700,-12,2,0,{"2":[]},0,[7,8],0,{"0":[]},{"0":[]},0,true,false],[168,"Interior Spawn DesertRuinLeftRoom_168",34,-28,-11,10,{"4":[]},0,[],144,{"0":[]},{"0":[]},0,true,false],[264,"IronCaveInteriorBolete2",250,6,6,0,{"4":[]},0,[],79,{"0":[]},{"0":[]},0,true,true],[247,"Interior Spawn HeimlichsHouse_247",40,0,-6,0,{"3":[]},10001,[],0,{"0":[]},{"0":[]},0,false,false],[5002,"PrefabRuinVines2",5000,0,-6,0,{"4":[]},0,[],156,{"0":[]},{"0":[]},0,true,false],[1008,"GreatHallPillar1",1000,0,10,0,{"3":[]},70000,[],0,{"0":[]},{"0":[]},0,false,false],[99999,"DevLadder",99999,0,0,0,{"3":[]},10001,[],0,{"0":[]},{"0":[]},0,false,false],[87,"Interior Spawn RightPowerCoreRoom_87",18,0,8,0,{"4":[]},0,[],200,{"0":[]},{"0":[]},0,true,false],[86,"Interior Spawn RightPowerCoreRoom_86",18,0,0,0,{"3":[]},10001,[],0,{"0":[]},{"0":[]},0,false,false],[779,"PuzzleRuinAncientChest19",700,-13,14,0,{"2":[]},0,[7,8],0,{"0":[]},{"0":[]},0,true,false],[1103,"GreatHallFinalRoomExit2",1100,6,12,0,{"3":[]},10001,[],0,{"0":[]},{"0":[]},0,false,false],[711,"PuzzleRuinSafeRubble2",700,-9,2,0,{"4":[]},0,[],158,{"0":[]},{"0":[]},0,true,false],[5103,"PrefabRuin2Roots3",5100,1,-6,0,{"4":[]},0,[],157,{"0":[]},{"0":[]},0,true,false],[704,"PuzzleRuinInteriorPillar4",700,-13,16,0,{"3":[]},70000,[],0,{"0":[]},{"0":[]},0,true,false],[754,"PuzzleRuinRubble35",700,-6,20,0,{"4":[]},0,[],158,{"0":[]},{"0":[]},0,true,true],[707,"PuzzleRuinInteriorPillar7",700,6,16,0,{"3":[]},70000,[],0,{"0":[]},{"0":[]},0,true,false],[516,"CollapsingRuinRubble16",500,1,16,0,{"4":[]},0,[],158,{"0":[]},{"0":[]},0,true,true],[25103,"T2PrefabRuin2Roots3",25100,1,-6,0,{"4":[]},0,[],176,{"0":[]},{"0":[]},0,true,false],[1210,"GreatHallWestHallwayChest4",1200,-22,7,0,{"2":[]},0,[7,8],0,{"0":[]},{"0":[]},0,true,false],[504,"CollapsingRuinRubble4",500,11,12,0,{"4":[]},0,[],158,{"0":[]},{"0":[]},0,true,false],[93,"Interior Spawn LeverDoorRoom_93",13,1,18,2,{"4":[]},0,[],143,{"0":[]},{"0":[]},0,true,false],[756,"PuzzleRuinRubble37",700,13,24,0,{"4":[]},0,[],158,{"0":[]},{"0":[]},0,true,true],[238,"Interior Spawn DesertRuinMainRoom_238",33,-9,2,0,{"3":[]},10001,[],0,{"0":[]},{"0":[]},0,false,false],[773,"PuzzleRuinAncientChest13",700,9,8,0,{"2":[]},0,[7,8],0,{"0":[]},{"0":[]},0,true,false],[117,"Interior Spawn SmallSturdyTownhouseLobby_117",20,-2,4,0,{"3":[]},10001,[],0,{"0":[]},{"0":[]},0,false,false],[1037,"GreatHallSafeTorch2",1000,5,26,0,{"4":[]},0,[],167,{"0":[]},{"0":[]},0,true,false],[1054,"Interior Spawn GreatHallRuin_1054",1000,1,10,6,{"4":[]},0,[],142,{"0":[]},{"0":[]},0,true,false],[1551,"GreatHallEntranceNextRoom",1050,0,18,0,{"3":[]},10001,[],0,{"0":[]},{"0":[]},0,false,false],[1560,"GreatHallEntranceVine3",1050,1,2,0,{"4":[]},0,[],175,{"0":[]},{"0":[]},0,true,false],[163,"Interior Spawn DesertRuinLeftRoom_163",34,-16,2,0,{"4":[]},0,[],215,{"0":[]},{"0":[]},0,true,false],[133,"Interior Spawn LargeSturdyTownhouseTopLeftRoom_133",28,2,-4,0,{"3":[]},10001,[],0,{"0":[]},{"0":[]},0,false,false],[1202,"GreatHallWestHallwayRubble2",1200,-13,-2,0,{"4":[]},0,[],158,{"0":[]},{"0":[]},0,true,false],[1021,"GreatHallAncientChest",1000,-2,30,0,{"2":[]},0,[7,8],0,{"0":[]},{"0":[]},0,true,false],[1300,"GreatHallEastHallwayEntrance",1300,0,0,0,{"3":[]},10001,[],0,{"0":[]},{"0":[]},0,false,false],[118,"Interior Spawn SmallSturdyTownhouseLobby_118",20,4,0,0,{"3":[]},10001,[],0,{"0":[]},{"0":[]},0,false,false],[755,"PuzzleRuinRubble36",700,0,20,0,{"4":[]},0,[],158,{"0":[]},{"0":[]},0,true,true],[126,"Interior Spawn LargeSturdyTownhouseLobby_126",25,-2,4,0,{"3":[]},10001,[],0,{"0":[]},{"0":[]},0,false,false],[740,"PuzzleRuinRubble21",700,-6,8,0,{"4":[]},0,[],158,{"0":[]},{"0":[]},0,true,true],[2004,"MazeRuinRoom5Pillar2",2000,-2,12,2,{"3":[]},70000,[],0,{"0":[]},{"0":[]},0,false,false],[26003,"T2LargeRuinPillar3",26000,1,4,0,{"3":[]},70000,[],0,{"0":[]},{"0":[]},0,false,false],[26017,"T2LargeRuinVine1",26000,6,-6,0,{"4":[]},0,[],175,{"0":[]},{"0":[]},0,true,false],[25006,"T2PrefabRuinChest3",25000,0,2,4,{"2":[]},0,[17,18],0,{"0":[]},{"0":[]},0,true,false],[26030,"Interior Spawn T2LargeRuin_26030",26000,5,9,6,{"4":[]},0,[],142,{"0":[]},{"0":[]},0,true,false],[1911,"Interior Spawn MazeRuinRoom4_1911",1900,1,14,6,{"4":[]},0,[],143,{"0":[]},{"0":[]},0,true,false],[27004,"T2LargeRuinTrapDoorKeyPillar",27000,6,12,0,{"4":[]},0,[],186,{"0":[]},{"0":[]},0,true,true],[28006,"T2LargeRuinFinalRoomPillar2",28000,2,12,0,{"3":[]},70000,[],0,{"0":[]},{"0":[]},0,false,false],[1902,"MazeRuinRoom4Brazier",1900,0,10,2,{"4":[]},0,[],179,{"0":[]},{"0":[]},0,true,false],[28009,"Interior Spawn T2LargeRuinFinalRoom_28009",28000,7,10,6,{"4":[]},0,[],144,{"0":[]},{"0":[]},0,true,false],[1606,"MazeRuinRoom1Pillar4",1600,2,8,2,{"3":[]},70001,[],0,{"0":[]},{"0":[]},0,false,false],[313,"LargeCaveLimestoneBoulder2",300,1,24,0,{"4":[]},0,[],40,{"0":[]},{"0":[]},0,true,true],[102,"Interior Spawn SmallCaveCopper_102",100,-1,6,0,{"4":[]},0,[],74,{"0":[]},{"0":[]},0,true,false],[752,"PuzzleRuinRubble33",700,0,20,0,{"4":[]},0,[],158,{"0":[]},{"0":[]},0,true,true],[227,"Interior Spawn DesertRuinFinalRoom_227",36,0,8,10,{"2":[]},0,[22],0,{"0":[]},{"0":[]},0,true,true],[1507,"GreatHallSafeRoomPillar4",1500,11,8,0,{"3":[]},70000,[],0,{"0":[]},{"0":[]},0,false,false],[137,"Interior Spawn SmallSturdyHouseRoom_137",32,2,-4,0,{"3":[]},10001,[],0,{"0":[]},{"0":[]},0,false,false],[75,"Interior Spawn LeftPowerCoreRoom_75",17,0,3,2,{"4":[]},0,[],198,{"0":[]},{"0":[]},0,true,false],[781,"PuzzleRuinAncientChest21",700,9,20,0,{"2":[]},0,[7,8],0,{"0":[]},{"0":[]},0,true,false],[1901,"MazeRuinRoom4FloorDecoration",1900,0,10,0,{"3":[]},70002,[],0,{"0":[]},{"0":[]},0,false,false],[776,"PuzzleRuinAncientChest16",700,6,14,0,{"2":[]},0,[7,8],0,{"0":[]},{"0":[]},0,true,false],[79,"Interior Spawn LeftPowerCoreRoom_79",17,1,12,2,{"4":[]},0,[],146,{"0":[]},{"0":[]},0,true,false],[1557,"GreatHallEntranceRubbleBuilding2",1050,6,9,6,{"3":[]},70003,[],0,{"0":[]},{"0":[]},0,false,false],[613,"LargeRuinInteriorAncientChest12",600,33,34,0,{"2":[]},0,[7,8,9],0,{"0":[]},{"0":[]},0,true,false],[81,"Interior Spawn LeftPowerCoreRoom_81",17,-4,4,0,{"4":[]},0,[],141,{"0":[]},{"0":[]},0,true,false],[789,"Interior Spawn PuzzleRuinInterior_789",700,4,38,6,{"4":[]},0,[],141,{"0":[]},{"0":[]},0,true,false],[1412,"GreatHallWestTorchRoomPillar4",1400,11,12,0,{"3":[]},70000,[],0,{"0":[]},{"0":[]},0,false,false],[122,"Interior Spawn SmallSturdyTownhouseTopRightRoom_122",23,2,-4,0,{"3":[]},10001,[],0,{"0":[]},{"0":[]},0,false,false],[1910,"MazeRuinRoom4Pillar",1900,0,8,2,{"4":[]},0,[],180,{"0":[]},{"0":[]},0,true,false],[2008,"MazeRuinRoom5BackToStartLadder",2000,-6,10,0,{"3":[]},10001,[],0,{"0":[]},{"0":[]},0,false,false],[307,"LargeCaveCopperVein3",300,1,10,0,{"4":[]},0,[],58,{"0":[]},{"0":[]},0,true,false],[5108,"Interior Spawn SingleRoomPrefabRuin2_5108",5100,0,4,2,{"4":[]},0,[],141,{"0":[]},{"0":[]},0,true,false],[244,"Interior Spawn T3SmallHouse_244",37,0,0,0,{"3":[]},10001,[],0,{"0":[]},{"0":[]},0,false,false],[37,"Interior Spawn LeftConnectorRoom_37",15,-14,5,4,{"4":[]},0,[],199,{"0":[]},{"0":[]},0,true,false],[20,"Interior Spawn LeverDoorRoom_20",13,12,4,0,{"3":[]},10001,[],0,{"0":[]},{"0":[]},0,false,false],[214,"TinCaveTinVein",200,0,8,0,{"4":[]},0,[],61,{"0":[]},{"0":[]},0,true,false],[1806,"MazeRuinRoom3Pillar4",1800,2,8,2,{"3":[]},70000,[],0,{"0":[]},{"0":[]},0,false,false],[12,"SpawnedT2SmallInteriorExitLadder",9,0,0,0,{"3":[]},10001,[],0,{"0":[]},{"0":[]},0,false,false],[1501,"GreatHallSafeRoomLargeRubble",1500,7,5,1,{"4":[]},0,[],172,{"0":[]},{"0":[]},0,true,false],[25100,"T2PrefabRuin2Entrance",25100,0,-8,0,{"3":[]},10001,[],0,{"0":[]},{"0":[]},0,false,false],[1801,"MazeRuinRoom3FloorDecoration",1800,0,10,0,{"3":[]},70002,[],0,{"0":[]},{"0":[]},0,false,false],[1200,"GreatHallWestHallwayEntrance",1200,0,0,0,{"3":[]},10001,[],0,{"0":[]},{"0":[]},0,false,false],[1608,"MazeRuinRoom1NextRoomLadder",1600,0,16,0,{"3":[]},10001,[],0,{"0":[]},{"0":[]},0,false,false],[26029,"Interior Spawn T2LargeRuin_26029",26000,16,2,8,{"4":[]},0,[],142,{"0":[]},{"0":[]},0,true,false],[507,"CollapsingRuinRubble7",500,9,16,0,{"4":[]},0,[],158,{"0":[]},{"0":[]},0,true,true],[100,"CopperCaveInteriorLadder",100,0,0,0,{"3":[]},10001,[],0,{"0":[]},{"0":[]},0,false,false],[1709,"MazeRuinRoom2BackToStartLadder2",1700,6,10,0,{"3":[]},10001,[],0,{"0":[]},{"0":[]},0,false,false],[72,"Interior Spawn LeftConnectorRoom_72",15,-15,-2,0,{"3":[]},10001,[],0,{"0":[]},{"0":[]},0,false,false],[85,"Interior Spawn LightPuzzleDungeonRoom_85",16,1,22,2,{"4":[]},0,[],144,{"0":[]},{"0":[]},0,true,false],[2007,"MazeRuinRoom5NextRoomLadder",2000,0,16,0,{"3":[]},10001,[],0,{"0":[]},{"0":[]},0,false,false],[10,"SpawnedMultiRoomCenterRoomExit",7,0,0,0,{"3":[]},10001,[],0,{"0":[]},{"0":[]},0,false,false],[1804,"MazeRuinRoom3Pillar2",1800,-2,12,2,{"3":[]},70001,[],0,{"0":[]},{"0":[]},0,false,false],[1110,"GreatHallFinalRoomFloorDecoration",1100,4,8,0,{"3":[]},70002,[],0,{"0":[]},{"0":[]},0,false,false],[518,"CollapsingRuinRubble18",500,2,16,0,{"4":[]},0,[],158,{"0":[]},{"0":[]},0,true,true],[608,"LargeRuinInteriorAncientChest7",600,15,16,0,{"2":[]},0,[7,8,9],0,{"0":[]},{"0":[]},0,true,false],[2014,"MazeRuinRoomUnsafeRubble2",2000,-5,10,0,{"4":[]},0,[],158,{"0":[]},{"0":[]},0,true,true],[76,"Interior Spawn LeftPowerCoreRoom_76",17,-4,11,10,{"2":[]},0,[18],0,{"0":[]},{"0":[]},0,true,false],[25003,"T2PrefabRuinVines3",25000,1,-6,0,{"4":[]},0,[],175,{"0":[]},{"0":[]},0,true,false],[128,"Interior Spawn LargeSturdyTownhouseLobby_128",25,5,3,0,{"3":[]},10001,[],0,{"0":[]},{"0":[]},0,false,false],[1044,"GreatHallNextRoomLadder",1000,18,36,0,{"3":[]},10001,[],0,{"0":[]},{"0":[]},0,false,false],[132,"Interior Spawn LargeSturdyTownhouseMidLeftRoom_132",27,2,-4,0,{"3":[]},10001,[],0,{"0":[]},{"0":[]},0,false,false],[98,"Interior Spawn Final Reward Room_98",19,0,8,10,{"2":[]},0,[20],0,{"0":[]},{"0":[]},0,true,false],[138,"Interior Spawn DesertRuinMainRoom_138",33,-2,-2,0,{"3":[]},70000,[],0,{"0":[]},{"0":[]},0,false,false],[1012,"GreatHallPillar5",1000,4,18,0,{"3":[]},70000,[],0,{"0":[]},{"0":[]},0,false,false],[1303,"GreatHallEastHallwayTorch3",1300,6,12,0,{"4":[]},0,[],168,{"0":[]},{"0":[]},0,true,false],[248,"Interior Spawn HeimlichsHouse_248",40,0,2,6,{"1":[]},0,[],0,{"0":[]},{"3":[]},8,true,false],[25109,"Interior Spawn T2SingleRoomPrefabRuin1_5010",25100,-2,2,10,{"3":[]},60,[],0,{"0":[]},{"0":[]},0,false,false],[771,"PuzzleRuinAncientChest11",700,-3,8,0,{"2":[]},0,[7,8],0,{"0":[]},{"0":[]},0,true,false],[715,"PuzzleRuinSafeRubble6",700,-3,14,0,{"4":[]},0,[],158,{"0":[]},{"0":[]},0,true,false],[1565,"GreatHallEntrancePillar3",1050,4,15,0,{"3":[]},70000,[],0,{"0":[]},{"0":[]},0,false,false],[40,"Interior Spawn LightPuzzleDungeonRoom_40",16,0,0,0,{"4":[]},0,[],203,{"0":[]},{"0":[]},0,true,false],[1420,"GreatHallWestTorchRoomFloorDecoration",1400,5,10,0,{"3":[]},70002,[],0,{"0":[]},{"0":[]},0,false,false],[775,"PuzzleRuinAncientChest15",700,12,14,0,{"2":[]},0,[7,8],0,{"0":[]},{"0":[]},0,true,false],[1505,"GreatHallSafeRoomPillar2",1500,3,16,0,{"3":[]},70000,[],0,{"0":[]},{"0":[]},0,false,false],[1408,"GreatHallWestTorchRoomExteriorExit3",1400,-4,20,0,{"3":[]},10001,[],0,{"0":[]},{"0":[]},0,false,false],[1559,"GreatHallEntranceVine2",1050,0,2,0,{"4":[]},0,[],175,{"0":[]},{"0":[]},0,true,false],[5000,"PrefabRuinEntrance",5000,0,-8,0,{"3":[]},10001,[],0,{"0":[]},{"0":[]},0,false,false],[27007,"T2LargeRuinTrapPillar2",27000,2,12,0,{"3":[]},70000,[],0,{"0":[]},{"0":[]},0,false,false],[1032,"GreatHallAncientChest12",1000,-10,20,0,{"2":[]},0,[7,8],0,{"0":[]},{"0":[]},0,true,false],[783,"PuzzleRuinAncientChest23",700,-3,20,0,{"2":[]},0,[7,8],0,{"0":[]},{"0":[]},0,true,false],[600,"LargeRuinInteriorExitLadder",600,0,0,0,{"3":[]},10001,[],0,{"0":[]},{"0":[]},0,false,false],[785,"PuzzleRuinRubble39",700,9,2,0,{"4":[]},0,[],158,{"0":[]},{"0":[]},0,true,true],[28007,"T2LargeRuinFinalRoomPillar3",28000,8,8,0,{"3":[]},70000,[],0,{"0":[]},{"0":[]},0,false,false],[152,"Interior Spawn DesertRuinRightRoom_152",35,9,16,0,{"3":[]},70000,[],0,{"0":[]},{"0":[]},0,false,false],[266,"Interior Spawn T4MediumHouse_266",48,-1,-2,0,{"3":[]},10001,[],0,{"0":[]},{"0":[]},0,false,false],[250,"IronCaveInteriorLadder",250,0,0,0,{"3":[]},10001,[],0,{"0":[]},{"0":[]},0,false,false],[1506,"GreatHallSafeRoomPillar3",1500,11,16,0,{"3":[]},70000,[],0,{"0":[]},{"0":[]},0,false,false],[5102,"PrefabRuin2Roots2",5100,0,-6,0,{"4":[]},0,[],157,{"0":[]},{"0":[]},0,true,false],[1212,"GreatHallWestHallwayTorches",1200,-16,18,0,{"4":[]},0,[],167,{"0":[]},{"0":[]},0,true,false],[512,"CollapsingRuinRubble12",500,7,16,0,{"4":[]},0,[],158,{"0":[]},{"0":[]},0,true,true],[191,"Interior Spawn DesertRuinRightRoom_191",35,30,12,0,{"4":[]},0,[],219,{"0":[]},{"0":[]},0,true,false],[19,"Interior Spawn LeverDoorRoom_19",13,0,-4,0,{"3":[]},10001,[],0,{"0":[]},{"0":[]},0,false,false],[701,"PuzzleRuinInteriorPillar1",700,-7,0,0,{"3":[]},70000,[],0,{"0":[]},{"0":[]},0,true,false],[223,"Interior Spawn DesertRuinFinalRoom_223",36,-2,8,4,{"4":[]},0,[],144,{"0":[]},{"0":[]},0,true,false],[700,"PuzzleRuinInteriorExitLadder",700,0,0,0,{"3":[]},10001,[],0,{"0":[]},{"0":[]},0,false,false],[89,"Interior Spawn RightPowerCoreRoom_89",18,4,12,2,{"4":[]},0,[],146,{"0":[]},{"0":[]},0,true,false],[232,"Interior Spawn DesertRuinRightRoom_232",35,28,6,4,{"2":[]},0,[21],0,{"0":[]},{"0":[]},0,true,false],[99,"Interior Spawn SmallSturdyTownhouseLobby_99",20,-1,-3,0,{"3":[]},10001,[],0,{"0":[]},{"0":[]},0,false,false],[1413,"GreatHallWestTorchRoomHintChest",1400,3,7,0,{"4":[]},0,[],182,{"0":[]},{"0":[]},0,true,false],[5003,"PrefabRuinVines3",5000,1,-6,0,{"4":[]},0,[],156,{"0":[]},{"0":[]},0,true,false],[1903,"MazeRuinRoom4Pillar1",1900,-2,8,2,{"3":[]},70001,[],0,{"0":[]},{"0":[]},0,false,false],[245,"Interior Spawn T3MediumHouse_245",38,0,0,0,{"3":[]},10001,[],0,{"0":[]},{"0":[]},0,false,false],[1000,"GreatHallPrimaryExitLadder",1000,0,0,0,{"3":[]},10001,[],0,{"0":[]},{"0":[]},0,false,false],[1803,"MazeRuinRoom3Pillar1",1800,-2,8,2,{"3":[]},70001,[],0,{"0":[]},{"0":[]},0,false,false],[25009,"Interior Spawn T2SingleRoomPrefabRuin2_5010",25000,-2,2,10,{"3":[]},60,[],0,{"0":[]},{"0":[]},0,false,false],[16,"Interior Spawn WindmillInteriorInstance_16",12,0,0,6,{"3":[]},3024,[],0,{"0":[]},{"0":[]},0,false,false],[1508,"Interior Spawn GreatHallSafeRoom_1508",1500,9,18,6,{"4":[]},0,[],144,{"0":[]},{"0":[]},0,true,false],[243,"Interior Spawn DesertRuinFinalRoom_243",36,0,-2,0,{"3":[]},10001,[],0,{"0":[]},{"0":[]},0,false,false],[39,"Interior Spawn LeftConnectorRoom_39",15,-5,7,2,{"4":[]},0,[],146,{"0":[]},{"0":[]},0,true,false],[1041,"GreatHallVine",1000,17,36,0,{"4":[]},0,[],175,{"0":[]},{"0":[]},0,true,false],[605,"LargeRuinInteriorAncientChest4",600,18,4,0,{"2":[]},0,[7,8,9],0,{"0":[]},{"0":[]},0,true,false],[1014,"GreatHallPillar7",1000,6,22,0,{"3":[]},70000,[],0,{"0":[]},{"0":[]},0,false,false],[1418,"GreatHallWestTorchRoomChest5",1400,15,7,0,{"2":[]},0,[7,8,9],0,{"0":[]},{"0":[]},0,true,false],[1045,"GreatHallAncientChest16",1000,7,20,0,{"2":[]},0,[7,8],0,{"0":[]},{"0":[]},0,true,false],[26005,"T2LargeRuinFloorDecor",26000,7,5,0,{"3":[]},70002,[],0,{"0":[]},{"0":[]},0,false,false],[237,"Interior Spawn DesertRuinRightRoom_237",35,18,12,0,{"4":[]},0,[],216,{"0":[]},{"0":[]},0,true,false],[140,"Interior Spawn DesertRuinMainRoom_140",33,2,-2,0,{"3":[]},70000,[],0,{"0":[]},{"0":[]},0,false,false],[91,"Interior Spawn RightPowerCoreRoom_91",18,-2,5,10,{"2":[]},0,[18],0,{"0":[]},{"0":[]},0,true,false],[153,"Interior Spawn DesertRuinRightRoom_153",35,15,8,0,{"3":[]},70000,[],0,{"0":[]},{"0":[]},0,false,false],[258,"IronCaveInteriorSandstoneDeposit3",250,1,2,0,{"4":[]},0,[],48,{"0":[]},{"0":[]},0,true,true],[719,"PuzzleRuinSafeRubble10",700,8,24,0,{"4":[]},0,[],158,{"0":[]},{"0":[]},0,true,true],[77,"Interior Spawn LeftPowerCoreRoom_77",17,3,11,10,{"2":[]},0,[18],0,{"0":[]},{"0":[]},0,true,false],[262,"IronCaveInteriorSwampBolete3",250,4,4,0,{"4":[]},0,[],81,{"0":[]},{"0":[]},0,true,true],[780,"PuzzleRuinAncientChest20",700,15,20,0,{"2":[]},0,[7,8],0,{"0":[]},{"0":[]},0,true,false],[634,"Interior Spawn LargeRuinInterior_634",600,33,32,10,{"4":[]},0,[],141,{"0":[]},{"0":[]},0,true,false],[2009,"MazeRuinRoom5BackToStartLadder2",2000,6,10,0,{"3":[]},10001,[],0,{"0":[]},{"0":[]},0,false,false],[23,"Interior Spawn LeftConnectorRoom_23",15,-7,22,0,{"4":[]},0,[],197,{"0":[]},{"0":[]},0,true,false],[114,"Interior Spawn MediumEnterableHutTier2_114",45,-1,-2,0,{"3":[]},10001,[],0,{"0":[]},{"0":[]},0,false,false],[1040,"GreatHallAncientChest15",1000,17,32,0,{"2":[]},0,[8,9],0,{"0":[]},{"0":[]},0,true,false],[206,"TinCaveLimestoneBoulder6",200,0,4,0,{"4":[]},0,[],46,{"0":[]},{"0":[]},0,true,false],[750,"PuzzleRuinRubble31",700,12,20,0,{"4":[]},0,[],158,{"0":[]},{"0":[]},0,true,true],[169,"Interior Spawn DesertRuinLeftRoom_169",34,-25,-11,10,{"4":[]},0,[],144,{"0":[]},{"0":[]},0,true,false],[1207,"GreatHallWestHallwayChest1",1200,-14,-8,0,{"2":[]},0,[7,8],0,{"0":[]},{"0":[]},0,true,false],[1904,"MazeRuinRoom4Pillar2",1900,-2,12,2,{"3":[]},70000,[],0,{"0":[]},{"0":[]},0,false,false],[175,"Interior Spawn DesertRuinMainRoom_175",33,2,4,6,{"4":[]},0,[],142,{"0":[]},{"0":[]},0,true,false],[71,"Interior Spawn LeftConnectorRoom_71",15,1,6,0,{"3":[]},10001,[],0,{"0":[]},{"0":[]},0,false,false],[1029,"GreatHallAncientChest9",1000,17,2,0,{"2":[]},0,[7,8],0,{"0":[]},{"0":[]},0,true,false],[2100,"MazeRuinLootRoomEntrance",2100,0,0,0,{"3":[]},10001,[],0,{"0":[]},{"0":[]},0,false,false],[160,"Interior Spawn DesertRuinLeftRoom_160",34,-8,4,0,{"4":[]},0,[],215,{"0":[]},{"0":[]},0,true,false],[26028,"T2LargeRuinNote",26000,1,2,0,{"4":[]},0,[],188,{"0":[]},{"0":[]},0,true,false],[162,"Interior Spawn DesertRuinLeftRoom_162",34,-17,2,0,{"4":[]},0,[],215,{"0":[]},{"0":[]},0,true,false],[741,"PuzzleRuinRubble22",700,-12,8,0,{"4":[]},0,[],158,{"0":[]},{"0":[]},0,true,true],[1567,"Interior Spawn GreatHallEntranceRoom_1567",1050,4,14,6,{"4":[]},0,[],142,{"0":[]},{"0":[]},0,true,false],[25001,"T2PrefabRuinVines",25000,-1,-6,0,{"4":[]},0,[],175,{"0":[]},{"0":[]},0,true,false],[80,"Interior Spawn LeftPowerCoreRoom_80",17,4,4,8,{"4":[]},0,[],141,{"0":[]},{"0":[]},0,true,false],[161,"Interior Spawn DesertRuinLeftRoom_161",34,-7,4,0,{"4":[]},0,[],215,{"0":[]},{"0":[]},0,true,false],[1908,"MazeRuinRoom4NextRoomLadder",1900,-6,10,0,{"3":[]},10001,[],0,{"0":[]},{"0":[]},0,false,false],[5001,"PrefabRuinVines",5000,-1,-6,0,{"4":[]},0,[],156,{"0":[]},{"0":[]},0,true,false],[31,"Interior Spawn LeverPuzzleDungeonMainRoom_31",14,-6,10,0,{"3":[]},70000,[],0,{"0":[]},{"0":[]},0,false,false],[25008,"HeimlichT2PrefabRuin2",25000,2,2,6,{"1":[]},0,[],0,{"0":[]},{"3":[]},8,false,false],[2105,"MazeRuinLootRoomPillar4",2100,8,8,2,{"3":[]},70000,[],0,{"0":[]},{"0":[]},0,false,false],[1609,"MazeRuinRoom1BackToStartLadder",1600,-6,10,0,{"3":[]},10001,[],0,{"0":[]},{"0":[]},0,false,false],[769,"PuzzleRuinAncientChest9",700,-15,8,0,{"2":[]},0,[7,8],0,{"0":[]},{"0":[]},0,true,false],[531,"CollapsingRuinChest2",500,14,28,0,{"2":[]},0,[7,8],0,{"0":[]},{"0":[]},0,true,false],[1604,"MazeRuinRoom1Pillar2",1600,-2,12,2,{"3":[]},70001,[],0,{"0":[]},{"0":[]},0,false,false],[1555,"GreatHallEntranceDoor",1050,0,17,2,{"4":[]},0,[],165,{"0":[]},{"0":[]},0,true,false],[26024,"T2LargeRuinRubble6",26000,3,7,0,{"4":[]},0,[],177,{"0":[]},{"0":[]},0,true,false],[180,"Interior Spawn DesertRuinMainRoom_180",33,6,2,0,{"4":[]},0,[],216,{"0":[]},{"0":[]},0,true,false],[1030,"GreatHallAncientChest10",1000,-11,20,0,{"2":[]},0,[7,8],0,{"0":[]},{"0":[]},0,true,false],[88,"Interior Spawn RightPowerCoreRoom_88",18,-4,12,2,{"4":[]},0,[],146,{"0":[]},{"0":[]},0,true,false],[195,"Interior Spawn DesertRuinRightRoom_195",35,12,14,10,{"4":[]},0,[],145,{"0":[]},{"0":[]},0,true,false],[763,"PuzzleRuinAncientChest3",700,3,32,0,{"2":[]},0,[16],0,{"0":[]},{"0":[]},0,true,false],[202,"TinCaveLimestoneBoulder2",200,0,2,0,{"4":[]},0,[],46,{"0":[]},{"0":[]},0,true,true],[1213,"GreatHallWestHallwayTorches2",1200,-14,18,0,{"4":[]},0,[],167,{"0":[]},{"0":[]},0,true,false],[174,"Interior Spawn DesertRuinMainRoom_174",33,-2,4,2,{"4":[]},0,[],142,{"0":[]},{"0":[]},0,true,false],[96,"Interior Spawn Final Reward Room_96",19,-4,12,2,{"4":[]},0,[],146,{"0":[]},{"0":[]},0,true,false],[620,"LargeRuinInteriorDoor1",600,-3,22,0,{"4":[]},0,[],159,{"0":[]},{"0":[]},0,true,false],[1053,"Interior Spawn GreatHallRuin_1053",1000,7,6,6,{"4":[]},0,[],142,{"0":[]},{"0":[]},0,true,false],[27,"Interior Spawn LeverPuzzleDungeonMainRoom_27",14,-3,2,0,{"3":[]},70000,[],0,{"0":[]},{"0":[]},0,false,false],[7,"SpawnedMultiRoomLobbyCenterExit",5,0,12,0,{"3":[]},10001,[],0,{"0":[]},{"0":[]},0,false,false],[165,"Interior Spawn DesertRuinLeftRoom_165",34,-8,16,0,{"4":[]},0,[],217,{"0":[]},{"0":[]},0,true,false],[737,"PuzzleRuinRubble18",700,12,8,0,{"4":[]},0,[],158,{"0":[]},{"0":[]},0,true,true],[34,"Interior Spawn LeverPuzzleDungeonMainRoom_34",14,1,13,2,{"4":[]},0,[],195,{"0":[]},{"0":[]},0,true,false],[1211,"GreatHallWestHallwayNextRoom",1200,-15,26,0,{"3":[]},10001,[],0,{"0":[]},{"0":[]},0,false,false],[27008,"T2LargeRuinTrapPillar3",27000,8,8,0,{"3":[]},70000,[],0,{"0":[]},{"0":[]},0,false,false],[42,"Interior Spawn LightPuzzleDungeonRoom_42",16,-8,1,0,{"4":[]},0,[],201,{"0":[]},{"0":[]},0,true,false],[46,"Interior Spawn LightPuzzleDungeonRoom_46",16,-2,13,0,{"4":[]},0,[],201,{"0":[]},{"0":[]},0,true,false],[50,"Interior Spawn LightPuzzleDungeonRoom_50",16,10,1,0,{"4":[]},0,[],202,{"0":[]},{"0":[]},0,true,false],[1410,"GreatHallWestTorchRoomPillar2",1400,-1,8,0,{"3":[]},70000,[],0,{"0":[]},{"0":[]},0,false,false],[1415,"GreatHallWestTorchRoomChest2",1400,7,9,0,{"2":[]},0,[8,9],0,{"0":[]},{"0":[]},0,true,false],[54,"Interior Spawn LightPuzzleDungeonRoom_54",16,-5,3,2,{"4":[]},0,[],202,{"0":[]},{"0":[]},0,true,false],[59,"Interior Spawn LightPuzzleDungeonRoom_59",16,10,13,0,{"4":[]},0,[],202,{"0":[]},{"0":[]},0,true,false],[1036,"GreatHallSafeTorch",1000,11,6,0,{"4":[]},0,[],167,{"0":[]},{"0":[]},0,true,false],[1401,"GreatHallWestTorchRoomGate1",1400,-3,12,0,{"4":[]},0,[],166,{"0":[]},{"0":[]},0,true,true],[63,"Interior Spawn LightPuzzleDungeonRoom_63",16,-5,9,2,{"4":[]},0,[],202,{"0":[]},{"0":[]},0,true,false],[130,"Interior Spawn LargeSturdyTownhouseLobby_130",25,2,-3,0,{"3":[]},10001,[],0,{"0":[]},{"0":[]},0,false,false],[178,"Interior Spawn DesertRuinMainRoom_178",33,-6,3,0,{"4":[]},0,[],217,{"0":[]},{"0":[]},0,true,false],[2102,"MazeRuinLootRoomPillar1",2100,2,12,2,{"3":[]},70000,[],0,{"0":[]},{"0":[]},0,false,false],[55,"Interior Spawn LightPuzzleDungeonRoom_55",16,-9,6,6,{"4":[]},0,[],202,{"0":[]},{"0":[]},0,true,false],[1809,"MazeRuinRoom3NextRoomLadder",1800,6,10,0,{"3":[]},10001,[],0,{"0":[]},{"0":[]},0,false,false],[1504,"GreatHallSafeRoomPillar1",1500,3,8,0,{"3":[]},70000,[],0,{"0":[]},{"0":[]},0,false,false],[8,"SpawnedMultiRoomLobbyRightExit",5,5,7,0,{"3":[]},10001,[],0,{"0":[]},{"0":[]},0,false,false],[70,"Interior Spawn LeverPuzzleDungeonMainRoom_70",14,3,9,2,{"4":[]},0,[],145,{"0":[]},{"0":[]},0,true,false],[44,"Interior Spawn LightPuzzleDungeonRoom_44",16,-11,9,2,{"4":[]},0,[],201,{"0":[]},{"0":[]},0,true,false],[48,"Interior Spawn LightPuzzleDungeonRoom_48",16,7,15,2,{"4":[]},0,[],201,{"0":[]},{"0":[]},0,true,false],[52,"Interior Spawn LightPuzzleDungeonRoom_52",16,7,3,2,{"4":[]},0,[],202,{"0":[]},{"0":[]},0,true,false],[57,"Interior Spawn LightPuzzleDungeonRoom_57",16,4,7,0,{"4":[]},0,[],202,{"0":[]},{"0":[]},0,true,false],[61,"Interior Spawn LightPuzzleDungeonRoom_61",16,7,9,2,{"4":[]},0,[],202,{"0":[]},{"0":[]},0,true,false],[65,"Interior Spawn LightPuzzleDungeonRoom_65",16,1,15,2,{"4":[]},0,[],202,{"0":[]},{"0":[]},0,true,false],[1406,"GreatHallWestTorchRoomExteriorExit",1400,14,0,0,{"3":[]},10001,[],0,{"0":[]},{"0":[]},0,false,false],[141,"Interior Spawn DesertRuinMainRoom_141",33,3,5,0,{"3":[]},70000,[],0,{"0":[]},{"0":[]},0,false,false],[181,"Interior Spawn DesertRuinMainRoom_181",33,7,3,0,{"4":[]},0,[],216,{"0":[]},{"0":[]},0,true,false],[1304,"GreatHallEastHallwayTorch4",1300,18,4,0,{"4":[]},0,[],168,{"0":[]},{"0":[]},0,true,false],[200,"TinCaveInteriorLadder",200,0,0,0,{"3":[]},10001,[],0,{"0":[]},{"0":[]},0,false,false],[25007,"Interior Spawn T2SingleRoomPrefabRuin1_25007",25000,0,4,2,{"4":[]},0,[],142,{"0":[]},{"0":[]},0,true,false],[708,"PuzzleRuinInteriorPillar8",700,9,10,0,{"3":[]},70000,[],0,{"0":[]},{"0":[]},0,true,false],[1602,"MazeRuinRoom1Brazier",1600,0,10,5,{"4":[]},0,[],173,{"0":[]},{"0":[]},0,true,false],[144,"Interior Spawn DesertRuinLeftRoom_144",34,-10,25,0,{"3":[]},70000,[],0,{"0":[]},{"0":[]},0,false,false],[1502,"GreatHallSafeRoomHexiteAxe",1500,7,14,0,{"4":[]},0,[],171,{"0":[]},{"0":[]},0,true,false],[184,"Interior Spawn DesertRuinRightRoom_184",35,7,-3,0,{"4":[]},0,[],216,{"0":[]},{"0":[]},0,true,false],[310,"LargeCaveButtonMushrooms2",300,-1,34,0,{"4":[]},0,[],74,{"0":[]},{"0":[]},0,true,false],[167,"Interior Spawn DesertRuinLeftRoom_167",34,-14,9,8,{"2":[]},0,[21],0,{"0":[]},{"0":[]},0,true,false],[635,"Interior Spawn LargeRuinInterior_635",600,33,38,6,{"4":[]},0,[],141,{"0":[]},{"0":[]},0,true,false],[403,"AncientWorkbenchRoomChest2",400,6,8,0,{"2":[]},0,[9],0,{"0":[]},{"0":[]},0,true,false],[157,"Interior Spawn DesertRuinRightRoom_157",35,23,7,0,{"3":[]},70000,[],0,{"0":[]},{"0":[]},0,false,false],[84,"Interior Spawn LightPuzzleDungeonRoom_84",16,-1,22,2,{"4":[]},0,[],145,{"0":[]},{"0":[]},0,true,false],[315,"LargeCaveLimestoneBoulder4",300,2,24,0,{"4":[]},0,[],40,{"0":[]},{"0":[]},0,true,true],[193,"Interior Spawn DesertRuinRightRoom_193",35,26,11,2,{"2":[]},0,[21],0,{"0":[]},{"0":[]},0,true,false],[751,"PuzzleRuinRubble32",700,6,20,0,{"4":[]},0,[],158,{"0":[]},{"0":[]},0,true,true],[1566,"GreatHallEntrancePillar4",1050,4,3,0,{"3":[]},70000,[],0,{"0":[]},{"0":[]},0,false,false],[2006,"MazeRuinRoom5Pillar4",2000,2,8,2,{"3":[]},70000,[],0,{"0":[]},{"0":[]},0,false,false],[616,"LargeRuinInteriorPillar1",600,34,32,0,{"3":[]},70000,[],0,{"0":[]},{"0":[]},0,true,false],[230,"Interior Spawn DesertRuinRightRoom_230",35,24,5,8,{"4":[]},0,[],141,{"0":[]},{"0":[]},0,true,false],[199,"Interior Spawn DesertRuinFinalRoom_199",36,-2,3,0,{"3":[]},70000,[],0,{"0":[]},{"0":[]},0,false,false],[252,"IronCaveInteriorIronOre",250,4,8,0,{"4":[]},0,[],62,{"0":[]},{"0":[]},0,true,true],[228,"Interior Spawn DesertRuinFinalRoom_228",36,5,5,0,{"2":[]},0,[21],0,{"0":[]},{"0":[]},0,true,false],[267,"Interior Spawn T5LargeHouse_267",43,-1,-1,0,{"3":[]},10001,[],0,{"0":[]},{"0":[]},0,false,false],[273,"Interior Spawn T6LargeHouse_273",52,-1,-1,0,{"3":[]},10001,[],0,{"0":[]},{"0":[]},0,false,false],[105,"Interior Spawn SmallCaveCopper_105",100,7,7,0,{"4":[]},0,[],74,{"0":[]},{"0":[]},0,true,false],[204,"TinCaveLimestoneBoulder4",200,4,9,0,{"4":[]},0,[],46,{"0":[]},{"0":[]},0,true,false],[211,"TinCaveBolete5",200,3,1,0,{"4":[]},0,[],79,{"0":[]},{"0":[]},0,true,false],[218,"TinCaveBolete7",200,3,9,0,{"4":[]},0,[],79,{"0":[]},{"0":[]},0,true,false],[259,"IronCaveInteriorSandstoneDeposit4",250,2,1,0,{"4":[]},0,[],48,{"0":[]},{"0":[]},0,true,true],[308,"LargeCaveCopperVein4",300,3,13,0,{"4":[]},0,[],58,{"0":[]},{"0":[]},0,true,false],[317,"LargeCaveButtonMushrooms4",300,6,17,0,{"4":[]},0,[],74,{"0":[]},{"0":[]},0,true,false],[501,"CollapsingRuinRubble1",500,13,11,0,{"4":[]},0,[],158,{"0":[]},{"0":[]},0,true,false],[509,"CollapsingRuinRubble9",500,8,17,0,{"4":[]},0,[],158,{"0":[]},{"0":[]},0,true,true],[517,"CollapsingRuinRubble17",500,2,15,0,{"4":[]},0,[],158,{"0":[]},{"0":[]},0,true,true],[523,"CollapsingRuinPillar4",500,10,15,0,{"3":[]},70001,[],0,{"0":[]},{"0":[]},0,true,false],[532,"CollapsingRuinChest3",500,13,29,0,{"2":[]},0,[7,8],0,{"0":[]},{"0":[]},0,true,false],[607,"LargeRuinInteriorAncientChest6",600,11,3,0,{"2":[]},0,[7,8],0,{"0":[]},{"0":[]},0,true,false],[615,"LargeRuinInteriorAncientChest14",600,12,33,0,{"2":[]},0,[7,8,9],0,{"0":[]},{"0":[]},0,true,false],[626,"LargeRuinInteriorRubble3",600,8,23,3,{"4":[]},0,[],158,{"0":[]},{"0":[]},0,true,false],[631,"LargeRuinInteriorRubble5",600,21,35,3,{"4":[]},0,[],158,{"0":[]},{"0":[]},0,true,true],[717,"PuzzleRuinSafeRubble8",700,8,11,0,{"4":[]},0,[],158,{"0":[]},{"0":[]},0,true,false],[722,"PuzzleRuinRubble3",700,-4,5,0,{"4":[]},0,[],158,{"0":[]},{"0":[]},0,true,true],[726,"PuzzleRuinRubble7",700,8,5,0,{"4":[]},0,[],158,{"0":[]},{"0":[]},0,true,true],[730,"PuzzleRuinRubble11",700,11,11,0,{"4":[]},0,[],158,{"0":[]},{"0":[]},0,true,true],[734,"PuzzleRuinRubble15",700,-4,11,0,{"4":[]},0,[],158,{"0":[]},{"0":[]},0,true,true],[743,"PuzzleRuinRubble24",700,2,17,0,{"4":[]},0,[],158,{"0":[]},{"0":[]},0,true,true],[747,"PuzzleRuinRubble28",700,-4,17,0,{"4":[]},0,[],158,{"0":[]},{"0":[]},0,true,true],[762,"PuzzleRuinAncientChest2",700,5,35,0,{"2":[]},0,[8,9],0,{"0":[]},{"0":[]},0,true,false],[1004,"GreatHallSafeDoor2",1000,14,5,0,{"4":[]},0,[],165,{"0":[]},{"0":[]},0,true,false],[1011,"GreatHallPillar4",1000,10,9,0,{"3":[]},70000,[],0,{"0":[]},{"0":[]},0,false,false],[1018,"GreatHallTree1",1000,13,27,0,{"4":[]},0,[],176,{"0":[]},{"0":[]},0,true,false],[1024,"GreatHallAncientChest4",1000,26,13,0,{"2":[]},0,[7,8],0,{"0":[]},{"0":[]},0,true,false],[1038,"GreatHallAncientChest13",1000,17,33,0,{"2":[]},0,[8,9],0,{"0":[]},{"0":[]},0,true,false],[1046,"GreatHallAncientChest17",1000,12,15,0,{"2":[]},0,[7,8],0,{"0":[]},{"0":[]},0,true,false],[1055,"Interior Spawn GreatHallRuin_1055",1000,20,31,6,{"4":[]},0,[],143,{"0":[]},{"0":[]},0,true,false],[1305,"GreatHallEastHallwayChest1",1300,13,11,0,{"2":[]},0,[8,9],0,{"0":[]},{"0":[]},0,true,false],[2015,"MazeRuinRoomUnsafeRubble3",2000,-4,9,0,{"4":[]},0,[],158,{"0":[]},{"0":[]},0,true,true],[2020,"Interior Spawn MazeRuinRoom5_2020",2000,-1,7,2,{"4":[]},0,[],142,{"0":[]},{"0":[]},0,true,false],[5004,"PrefabRuinChest1",5000,2,5,0,{"2":[]},0,[7,8,9],0,{"0":[]},{"0":[]},0,true,false],[5105,"PrefabRuin2Chest2",5100,-1,5,4,{"2":[]},0,[7,8,9],0,{"0":[]},{"0":[]},0,true,false],[25104,"T2PrefabRuin2Chest1",25100,2,5,0,{"2":[]},0,[17],0,{"0":[]},{"0":[]},0,true,false],[26021,"T2LargeRuinChest3",26000,4,-7,0,{"2":[]},0,[17],0,{"0":[]},{"0":[]},0,true,false],[27006,"T2LargeRuinTrapPillar1",27000,0,7,0,{"3":[]},70000,[],0,{"0":[]},{"0":[]},0,false,false],[28008,"T2LargeRuinFinalRoomPillar4",28000,6,3,0,{"3":[]},70000,[],0,{"0":[]},{"0":[]},0,false,false],[5107,"PrefabRuin2Note",5100,-2,1,0,{"4":[]},0,[],185,{"0":[]},{"0":[]},0,true,false],[25105,"T2PrefabRuin2Chest2",25100,-1,5,4,{"2":[]},0,[17],0,{"0":[]},{"0":[]},0,true,false],[26026,"T2LargeRuinRubble8",26000,6,-1,0,{"4":[]},0,[],177,{"0":[]},{"0":[]},0,true,false],[27009,"T2LargeRuinTrapPillar4",27000,6,3,0,{"3":[]},70000,[],0,{"0":[]},{"0":[]},0,false,false],[6,"SpawnedMultiRoomLobbyLeftExit",5,-4,7,0,{"3":[]},10001,[],0,{"0":[]},{"0":[]},0,false,false],[69,"Interior Spawn LeverPuzzleDungeonMainRoom_69",14,-2,9,2,{"4":[]},0,[],145,{"0":[]},{"0":[]},0,true,false],[43,"Interior Spawn LightPuzzleDungeonRoom_43",16,-11,3,2,{"4":[]},0,[],201,{"0":[]},{"0":[]},0,true,false],[47,"Interior Spawn LightPuzzleDungeonRoom_47",16,4,13,0,{"4":[]},0,[],201,{"0":[]},{"0":[]},0,true,false],[51,"Interior Spawn LightPuzzleDungeonRoom_51",16,13,3,2,{"4":[]},0,[],202,{"0":[]},{"0":[]},0,true,false],[56,"Interior Spawn LightPuzzleDungeonRoom_56",16,-2,7,0,{"4":[]},0,[],202,{"0":[]},{"0":[]},0,true,false],[60,"Interior Spawn LightPuzzleDungeonRoom_60",16,13,9,2,{"4":[]},0,[],202,{"0":[]},{"0":[]},0,true,false],[64,"Interior Spawn LightPuzzleDungeonRoom_64",16,-5,15,2,{"4":[]},0,[],202,{"0":[]},{"0":[]},0,true,false],[139,"Interior Spawn DesertRuinMainRoom_139",33,-2,5,0,{"3":[]},70000,[],0,{"0":[]},{"0":[]},0,false,false],[179,"Interior Spawn DesertRuinMainRoom_179",33,7,1,0,{"4":[]},0,[],216,{"0":[]},{"0":[]},0,true,false],[143,"Interior Spawn DesertRuinLeftRoom_143",34,-10,21,0,{"3":[]},70000,[],0,{"0":[]},{"0":[]},0,false,false],[164,"Interior Spawn DesertRuinLeftRoom_164",34,-7,27,0,{"4":[]},0,[],218,{"0":[]},{"0":[]},0,true,false],[156,"Interior Spawn DesertRuinRightRoom_156",35,29,17,0,{"3":[]},70000,[],0,{"0":[]},{"0":[]},0,false,false],[190,"Interior Spawn DesertRuinRightRoom_190",35,13,3,0,{"4":[]},0,[],217,{"0":[]},{"0":[]},0,true,false],[197,"Interior Spawn DesertRuinRightRoom_197",35,15,15,4,{"4":[]},0,[],143,{"0":[]},{"0":[]},0,true,false],[236,"Interior Spawn DesertRuinRightRoom_236",35,18,11,0,{"4":[]},0,[],216,{"0":[]},{"0":[]},0,true,false],[222,"Interior Spawn DesertRuinFinalRoom_222",36,3,9,0,{"3":[]},70000,[],0,{"0":[]},{"0":[]},0,false,false],[112,"Interior Spawn T5MediumHouse_112",42,-1,-3,0,{"3":[]},10001,[],0,{"0":[]},{"0":[]},0,false,false],[272,"Interior Spawn T6MediumHouse_272",51,-1,-3,0,{"3":[]},10001,[],0,{"0":[]},{"0":[]},0,false,false],[104,"Interior Spawn SmallCaveCopper_104",100,2,5,0,{"4":[]},0,[],74,{"0":[]},{"0":[]},0,true,false],[203,"TinCaveLimestoneBoulder3",200,2,1,0,{"4":[]},0,[],46,{"0":[]},{"0":[]},0,true,true],[208,"TinCaveBolete2",200,3,7,0,{"4":[]},0,[],79,{"0":[]},{"0":[]},0,true,false],[216,"TinCaveTinVein3",200,4,3,0,{"4":[]},0,[],61,{"0":[]},{"0":[]},0,true,false],[255,"IronCaveInteriorBasaltDeposit",250,2,9,0,{"4":[]},0,[],53,{"0":[]},{"0":[]},0,true,true],[306,"LargeCaveBolete3",300,1,9,0,{"4":[]},0,[],79,{"0":[]},{"0":[]},0,true,false],[316,"LargeCaveLimestoneBoulder5",300,2,23,0,{"4":[]},0,[],40,{"0":[]},{"0":[]},0,true,true],[405,"Interior Spawn AncientWorkbenchRoom_405",400,4,3,8,{"4":[]},0,[],144,{"0":[]},{"0":[]},0,true,false],[508,"CollapsingRuinRubble8",500,9,17,0,{"4":[]},0,[],158,{"0":[]},{"0":[]},0,true,true],[515,"CollapsingRuinRubble15",500,1,15,0,{"4":[]},0,[],158,{"0":[]},{"0":[]},0,true,true],[522,"CollapsingRuinPillar3",500,7,17,0,{"3":[]},70001,[],0,{"0":[]},{"0":[]},0,true,false],[530,"CollapsingRuinChest1",500,14,29,0,{"2":[]},0,[8],0,{"0":[]},{"0":[]},0,true,true],[606,"LargeRuinInteriorAncientChest5",600,12,3,0,{"2":[]},0,[7,8],0,{"0":[]},{"0":[]},0,true,false],[612,"LargeRuinInteriorAncientChest11",600,38,43,0,{"2":[]},0,[7,8],0,{"0":[]},{"0":[]},0,true,false],[625,"LargeRuinInteriorRubble2",600,7,23,3,{"4":[]},0,[],158,{"0":[]},{"0":[]},0,true,false],[629,"LargeRuinInteriorVines3",600,8,41,3,{"4":[]},0,[],156,{"0":[]},{"0":[]},0,true,false],[713,"PuzzleRuinSafeRubble4",700,-13,11,0,{"4":[]},0,[],158,{"0":[]},{"0":[]},0,true,false],[721,"PuzzleRuinRubble2",700,-7,5,0,{"4":[]},0,[],158,{"0":[]},{"0":[]},0,true,true],[725,"PuzzleRuinRubble6",700,5,5,0,{"4":[]},0,[],158,{"0":[]},{"0":[]},0,true,true],[729,"PuzzleRuinRubble10",700,14,11,0,{"4":[]},0,[],158,{"0":[]},{"0":[]},0,true,true],[733,"PuzzleRuinRubble14",700,-1,11,0,{"4":[]},0,[],158,{"0":[]},{"0":[]},0,true,true],[742,"PuzzleRuinRubble23",700,5,17,0,{"4":[]},0,[],158,{"0":[]},{"0":[]},0,true,true],[746,"PuzzleRuinRubble27",700,-1,17,0,{"4":[]},0,[],158,{"0":[]},{"0":[]},0,true,true],[761,"PuzzleRuinAncientChest",700,2,35,0,{"2":[]},0,[8,9],0,{"0":[]},{"0":[]},0,true,false],[1002,"GreatHallCollapsingDoor2",1000,20,17,0,{"4":[]},0,[],166,{"0":[]},{"0":[]},0,true,true],[1009,"GreatHallPillar2",1000,8,5,0,{"3":[]},70000,[],0,{"0":[]},{"0":[]},0,false,false],[1017,"GreatHallPillar10",1000,16,21,0,{"3":[]},70000,[],0,{"0":[]},{"0":[]},0,false,false],[1023,"GreatHallAncientChest3",1000,-2,31,0,{"2":[]},0,[7,8],0,{"0":[]},{"0":[]},0,true,false],[1031,"GreatHallAncientChest11",1000,-10,21,0,{"2":[]},0,[7,8],0,{"0":[]},{"0":[]},0,true,false],[1043,"GreatHallVine3",1000,19,35,0,{"4":[]},0,[],175,{"0":[]},{"0":[]},0,true,false],[1052,"GreatHallFloorDecoration",1000,8,15,0,{"3":[]},70002,[],0,{"0":[]},{"0":[]},0,false,false],[1109,"GreatHallFinalRoomChest3",1100,6,5,0,{"2":[]},0,[17,18],0,{"0":[]},{"0":[]},0,true,true],[2013,"MazeRuinRoomUnsafeRubble1",2000,-4,11,0,{"4":[]},0,[],158,{"0":[]},{"0":[]},0,true,true],[2019,"Interior Spawn MazeRuinRoom5_2019",2000,2,7,6,{"4":[]},0,[],142,{"0":[]},{"0":[]},0,true,false],[2109,"MazeRuinLootChest",2100,2,9,0,{"2":[]},0,[7,8,9],0,{"0":[]},{"0":[]},0,true,true]]}]